Workbook
Name TotalWeekRespondents: 'Аналитика'!$B$10
Name CurSprint: 'Аналитика'!$B$1

Sheet RawData
A1: timestamp | B1: session_id | C1: tg_id | D1: week | E1: group_id | F1: cubes_reactive | G1: cubes_proactive | H1: cubes_operational | I1: cubes_pool | J1: satisfaction | K1: representative | L1: work_life | M1: pss_1 | N1: pss_2 | O1: pss_3 | P1: pss_4 | Q1: takeaway | R1: comment | S1: time_total | T1: device_type | U1: Фактор дистресса | V1: Фактор совладания | W1: Воспринимаемый стресс
A2: 46208.376 | B2: 5501a13245b9a5b2133ed7b01a73fd31 | C2: artsm92 | D2: 0 | E2: 🔥%20Огоньки%20(ДС%202026q3) | F2: 4 | G2: 2 | H2: 0 | I2: 0 | J2: 4 | K2: -1 | L2: 1 | M2: 3 | N2: 3 | O2: 1 | P2: 3 | Q2: - одна задача в один момент времени, отключать уведомления в чатах где постоянно тегают - формулировка целей важна и размышления на тему где я сейчас | S2: 196 | T2: mobile | U2: {=M2:M642+P2:P642} -> 6 | V2: {=N2:N642+O2:O642} -> 4 | W2: {=U2:U642-V2:V642+8} -> 10
A3: 46208.417 | B3: b6d79df46cbaae1c89fa5ccc891b2b75 | C3: unfreeshooter | D3: 0 | E3: 🔥 Огоньки (ДС 2026q3) | F3: 3 | G3: 1 | H3: 2 | I3: 0 | J3: 6 | K3: -2 | L3: 0 | M3: 1 | N3: 3 | O3: 2 | P3: 1 | Q3: если делать и потом аналитить - почти все срабатывает на мне из практик. а если аналитить, а потом делать - делать будет нечего: все воспринимается лишь В ТЕОРИИ | R3: не очень показателен п2 "Насколько прошедшая неделя была похожа на ваш обычный режим работы?*" для меня: я из Севастополя, у нас внезапные отключения ЭЭ, что сильно влияет на формат работы. ну и пункты дальше тоже в разрезе проблем локальных с бензом и эл-вом/водой (пока только с ними)- все по фактам | S3: 736 | T3: desktop | U3: 2 | V3: 5 | W3: 5
A4: 46208.421 | B4: 1dd388c2279277f99a769060a5ed92df | C4: chernykh_irina | D4: 0 | E4: 💥%20Искорки%20(ДС%202026q3) | F4: 0 | G4: 2 | H4: 4 | I4: 0 | J4: 6 | K4: 1 | L4: 1 | M4: 0 | N4: 4 | O4: 4 | P4: 1 | Q4: Немножко почитала задачки и цели ребят на доске практики и поняла, что у меня в принципе нет опасений в жизни. Мои задачки все или рутинные или те, которые ведут меня к целям. По отдыху тоже интуитивно распределяю всякие классные активности, единственное в течение дня работаю и совсем не отдыхаю. Уже нашла пилатес-стулию рядом с работой, вот вернусь с командировки мечты и начну ходить по средам в обед на пилатес. И хочу потихоньку внедрять помидорки с отдыхом между ними и ретроспективу с командой по рабочим задачкам . | R4: Есть ощущение некоторой сумбурности в части просматриваемых видео. Понятно, что у вас уже накоплен багаж и одно и то же переснимать не сильно эффективно. Но например, ответы на вопросы с какой-то практики: Максим говорит про улитки так, что я уже должна быть сильно в теме, а мы ж ещё нигде не обсуждали их ☹️ На самой практике я не поняла почему до докопались с моей задачей «запросить документы для учебы», которую я привязала к цели «я настроила бизнес-процессы». Это же первый шажок к тому, чтобы научиться настраивать грамотно бизнес-процессы. Есть тут некоторое недопонимание, что за цель тогда должна быть, какой масштаб? Понимаю, что сложно выслушать все тройки, но ребята же могут просто не так понять и уйти в демагогию при обсуждении чьей-то цели. Кажется, что стоит делать акцент на длине чтобычтотора и вообще на то, что надо именно через «чтобы что» связывать задачу с целью. И рандомно выбирать хотя бы три таких связки для разбора под присмотром Максима не по комнатам, а при всё честнОм народе 🤗 | S4: 1074 | T4: mobile | U4: 1 | V4: 8 | W4: 1
A5: 46208.422 | B5: 4a30073f1ead1ba55d61a0be343d0577 | C5: Garikos8 | D5: 0 | E5: 🔥 Огоньки (ДС 2026q3) | F5: 3 | G5: 2 | H5: 1 | I5: 0 | J5: 6 | K5: 1 | L5: 1 | M5: 1 | N5: 3 | O5: 3 | P5: 1 | Q5: Мало составить план, надо уметь и двигаться по нему. | S5: 194 | T5: mobile | U5: 2 | V5: 6 | W5: 4
A6: 46208.433 | B6: a28815f6be6b96080aaa10769c623798 | C6: i1024i | D6: 0 | E6: 🌟%20Звёздочки%20(ДС%202026q3) | F6: 2 | G6: 3 | H6: 1 | I6: 0 | J6: 5 | K6: 1 | L6: 2 | M6: 2 | N6: 3 | O6: 2 | P6: 2 | Q6: Нужно планировать отдых, заранее определиться, как я буду отдыхать и использовать свободное время | S6: 116 | T6: mobile | U6: 4 | V6: 5 | W6: 7
A7: 46208.435 | B7: 4a5c4304337932162d21dade1831f645 | C7: tnikotyan | D7: 0 | E7: 💥 Искорки (ДС 2026q3) | F7: 4 | G7: 1 | H7: 1 | I7: 0 | J7: 4 | K7: -1 | L7: 1 | M7: 3 | N7: 2 | O7: 2 | P7: 3 | S7: 118 | T7: mobile | U7: 6 | V7: 4 | W7: 10
A8: 46208.436 | B8: 3de1e7bf0e4c2263132190427bb172e7 | C8: nvkoy | D8: 0 | E8: 🌟 Звёздочки (ДС 2026q3) | F8: 1 | G8: 4 | H8: 1 | I8: 0 | J8: 5 | K8: 1 | L8: 1 | M8: 1 | N8: 3 | O8: 3 | P8: 1 | Q8: "Чтобы что" сильно помогает избавиться от лишнего и расставить реальные приоритеты | R8: Вы лучшие! Спасибо! :) | S8: 185 | T8: desktop | U8: 2 | V8: 6 | W8: 4
A9: 46208.461 | B9: 4ba89f712442ebd55f3f6b203be24be0 | C9: dimisi | D9: 0 | E9: 💥 Искорки (ДС 2026q3) | F9: 1 | G9: 1 | H9: 2 | I9: 2 | J9: 7 | K9: 2 | L9: -2 | M9: 3 | N9: 3 | O9: 3 | P9: 4 | Q9: Отдыхать - крута! | S9: 133 | T9: desktop | U9: 7 | V9: 6 | W9: 9
A10: 46208.476 | B10: 98c4160f00a06c6698f9b03478083c04 | C10: oakimov | D10: 0 | E10: 🌟 Звёздочки (ДС 2026q3) | F10: 2 | G10: 0 | H10: 4 | I10: 0 | J10: 3 | K10: 1 | L10: 1 | M10: 2 | N10: 3 | O10: 3 | P10: 1 | Q10: Отдых - неотъемлемая часть грамотного труда | S10: 127 | T10: mobile | U10: 3 | V10: 6 | W10: 5
A11: 46208.482 | B11: 4bf2f7e9a7089a54f51634223dde8ef9 | C11: DarkJewel | D11: 0 | E11: 🌟 Звёздочки (ДС 2026q3) | F11: 1 | G11: 1 | H11: 2 | I11: 2 | J11: 6 | K11: 1 | L11: -2 | M11: 4 | N11: 1 | O11: 2 | P11: 4 | Q11: Читать художественные книги - мой вариант отдыха. | R11: Тяжёлая неделя, сделал очень мало. Ресурс в основном потрачен на поддержание жизни в тушке и на дохрена тревожных мыслей. НО! меня на этой неделе нашла работа, в понедельник выхожу на первую смену. | S11: 273 | T11: mobile | U11: 8 | V11: 3 | W11: 13
A12: 46208.54 | B12: a013009f551579acc6d31ae0fd2ffb29 | C12: fyodor5 | D12: 0 | E12: 💥 Искорки (ДС 2026q3) | F12: 1 | G12: 0 | H12: 1 | I12: 4 | J12: 2 | K12: -1 | L12: 0 | M12: 2 | N12: 3 | O12: 2 | P12: 0 | Q12: Мне необходимо внедрять рутины для фокуса на важных задачах для их выполнения, иначе я просто не сажусь их выполнять и разбираться. | S12: 150 | T12: desktop | U12: 2 | V12: 5 | W12: 5
A13: 46208.548 | B13: 950e34770b251536f8703a5140c506a3 | C13: n_Set | D13: 0 | E13: 💥 Искорки (ДС 2026q3) | F13: 0 | G13: 0 | H13: 0 | I13: 6 | J13: 4 | K13: 1 | L13: 1 | M13: 4 | N13: 3 | O13: 4 | P13: 3 | Q13: что давно забыл что мне именно интересно , так как часто перегружал себя работой, и когда приходит пора др я оч долго думаю чего бы я хотел, чаще говорю у меня все есть давайте деньгами | S13: 118 | T13: desktop | U13: 7 | V13: 7 | W13: 8
A14: 46208.554 | B14: 7bbad278ff70c5aa5f60086de71d2323 | C14: anna_metel87 | D14: 0 | E14: 🔥 Огоньки (ДС 2026q3) | F14: 1 | G14: 2 | H14: 3 | I14: 0 | J14: 6 | K14: 3 | L14: 0 | M14: 2 | N14: 3 | O14: 3 | P14: 0 | Q14: Из практики "чтобычтотор" - пожалуй, сам факт сформулированных целей. Из книги "Путь джедая" - что работать над зеленой задачей надо 1м делом за день и в любом состоянии и обстоятельствах, если хочешь прогресс. | R14: Вопрос: если задача понятна "обезьяне", но я все равно не хочу ее делать и поэтому откладываю - как мне решить эту проблему? По-хорошему, да, надо делегировать, это просто "не моя" задача, она не приближает меня ни к чему. Но я не могу ее спихнуть, это часть моих рабочих обязанностей, она недостаточна для найма целого человека (опять же NDA, чувствительные данные) и ее невозможно автоматизировать (там все что можно автоматизировано, мне финально просмотреть и каждый раз через боль🤪😁). | S14: 1611 | T14: mobile | U14: 2 | V14: 6 | W14: 4
A15: 46208.612 | B15: de27f4ae585a5b80d653f2d00f5d3feb | C15: victor_goriunov | D15: 0 | E15: 🌟 Звёздочки (ДС 2026q3) | F15: 2 | G15: 3 | H15: 1 | I15: 0 | J15: 6 | K15: 2 | L15: 2 | M15: 1 | N15: 3 | O15: 3 | P15: 2 | Q15: Via negativa. Не столько добавлять упражнения для отдыха, сколько НЕ делать лишнего. Есть предощущение, что текущий курс может сработать. | S15: 345 | T15: desktop | U15: 3 | V15: 6 | W15: 5
A16: 46208.621 | B16: 85727bd551d9a4576689d6beae69dee6 | C16: PalaVistas | D16: 0 | E16: 💥%20Искорки%20(ДС%202026q3) | F16: 2 | G16: 1 | H16: 1 | I16: 2 | J16: 2 | K16: -1 | L16: 0 | M16: 3 | N16: 2 | O16: 1 | P16: 3 | S16: 180 | T16: mobile | U16: 6 | V16: 3 | W16: 11
A17: 46208.63 | B17: 9ec07e9263d0206f098f5f4af3bf16f0 | C17: PolyakovaAR | D17: 0 | E17: 🌟 Звёздочки (ДС 2026q3) | F17: 0 | G17: 0 | H17: 0 | I17: 6 | J17: 4 | K17: 0 | L17: 0 | M17: 1 | N17: 3 | O17: 2 | P17: 2 | Q17: мне очень тяжело заставлять себя читать правила всех этих опросников тетрадей и прочего я не вижу в них ценности | S17: 125 | T17: desktop | U17: 3 | V17: 5 | W17: 6
A18: 46208.632 | B18: c493b0688a2309f5eb2a18ee2a9b24be | C18: kiralary | D18: 0 | E18: ☀️%20Лучики%20(ДС%202026q3) | F18: 2 | G18: 1 | H18: 2 | I18: 1 | J18: 6 | K18: 2 | L18: 1 | M18: 1 | N18: 3 | O18: 3 | P18: 1 | Q18: Можно отдыхать каждый день! Даже пять минут отдыха уже что-то значат. | R18: Спасибо за рекомендацию Анны Обуховой. Теперь слушаю её в свободное время | S18: 9401 | T18: mobile | U18: 2 | V18: 6 | W18: 4
A19: 46208.637 | B19: ac10cbb802efa6b77ccf890acaa30db2 | C19: basilmiron | D19: 0 | E19: ☀️ Лучики (ДС 2026q3) | F19: 2 | G19: 3 | H19: 1 | I19: 0 | J19: 5 | K19: 1 | L19: -2 | M19: 3 | N19: 2 | O19: 0 | P19: 1 | Q19: Хочешь чему-то научиться -- попробуй научить этому других. | R19: Хотелось бы большей вовлечённости участников -- пока что чат нашей группы в телеге потихоньку зарастает тиной и покрывается ряской 🥲 | S19: 192 | T19: desktop | U19: 4 | V19: 2 | W19: 10
A20: 46208.642 | B20: 4b2d6b105edba5b16e2937cd6c02300a | C20: LESNYAKSERGEY | D20: 0 | E20: ☀️ Лучики (ДС 2026q3) | F20: 3 | G20: 0 | H20: 1 | I20: 2 | J20: 2 | K20: 0 | L20: 2 | M20: 2 | N20: 2 | O20: 1 | P20: 3 | S20: 164 | T20: desktop | U20: 5 | V20: 3 | W20: 10
A21: 46208.674 | B21: 845c8863cec29d0b32eae38855a8d42c | C21: Olegkim0 | D21: 0 | E21: ☀️ Лучики (ДС 2026q3) | F21: 3 | G21: 3 | H21: 0 | I21: 0 | J21: 5 | K21: 2 | L21: 3 | M21: 3 | N21: 2 | O21: 3 | P21: 1 | S21: 81 | T21: mobile | U21: 4 | V21: 5 | W21: 7
A22: 46208.691 | B22: 4cb2ef87d139c0e0271a8281c30790cd | C22: shaklein_e | D22: 0 | E22: 🔥%20Огоньки%20(ДС%202026q3) | F22: 1 | G22: 3 | H22: 2 | I22: 0 | J22: 5 | K22: 1 | L22: 0 | M22: 1 | N22: 4 | O22: 3 | P22: 0 | Q22: Что живу содержательную и интересную жизнь | S22: 150 | T22: mobile | U22: 1 | V22: 7 | W22: 2
A23: 46208.704 | B23: 9ef2e0fec483bfa493bd00e2ce84f744 | C23: petrovgenq | D23: 0 | E23: чат | F23: 3 | G23: 0 | H23: 3 | I23: 0 | J23: 1 | K23: -3 | L23: 3 | M23: 3 | N23: 3 | O23: 2 | P23: 2 | Q23: Отдых это важно | R23: Спасибо за то, что вы делаете | S23: 302 | T23: desktop | U23: 5 | V23: 5 | W23: 8
A24: 46208.715 | B24: d81a06a6395aec67d6cf869068999809 | C24: elpaev | D24: 0 | E24: ☀️ Лучики (ДС 2026q3) | F24: 2 | G24: 1 | H24: 3 | I24: 0 | J24: 5 | K24: 0 | L24: -2 | M24: 2 | N24: 2 | O24: 3 | P24: 1 | S24: 145 | T24: mobile | U24: 3 | V24: 5 | W24: 6
A25: 46208.873 | B25: 3b2198a73517fc391fa71e547fb26be1 | C25: dhbdt | D25: 0 | E25: 🌟 Звёздочки (ДС 2026q3) | F25: 3 | G25: 1 | H25: 1 | I25: 1 | J25: 5 | K25: -1 | L25: 1 | M25: 1 | N25: 3 | O25: 3 | P25: 1 | Q25: Даже если прямо сейчас я не могу воспользоваться всеми накопленными знаниями/навыками, это не делает их бесполезными И это повод сфокусироваться не на приобретении новых, а на распаковывании этого багажа силы | S25: 527 | T25: mobile | U25: 2 | V25: 6 | W25: 4
A26: 46208.904 | B26: 3635adc097205b514c8c7bd033e85d97 | C26: grigory_sam | D26: 0 | E26: ☀️ Лучики (ДС 2026q3) | F26: 2 | G26: 2 | H26: 1 | I26: 1 | J26: 6 | K26: -2 | L26: 2 | M26: 2 | N26: 2 | O26: 2 | P26: 2 | Q26: Короткая версия - Парадоксально, что на неделе посвященной Отдыху я херачил как не в себя. Но постоянно держал в голове мысль о важности отдыха. Да и почувствовать эту важность получилось, когда энергию приходилось выскребать с самого дна. Для отдыха как будто бы не оставалось времени (там очень страшная красная задача, точнее проект). Так вот, удалось столкнуть жесткое пренебреждение отдыхом и осознание абсолютной необходимости в нём. И я нашел один из потерянных ключей к своей продуктивности - чрезвычайно важны понятные и конкретные мои собственные цели. Я теряю время в течение рабочего дня, потому что не могу сконцентрироваться и сделать даже что-то обезьянопонятное. Но как только у меня в трекере появилась связь задач с целями - это был настоящий буст. Инсайт сугубо личный. Есть немало людей, которые хорошо формулируют и представляют свои цели. Иметь кристально ясную, мою собственную, личную цель (которая ничем не оправдана, типа работы) - очень помогает быть эффективнее, даже когда энергии почти нет. | R26: Искренняя благодарность. Отдельно приятно, что у курса так хорошо развилась коммьюнити-составляющая, это здорово. | S26: 1370 | T26: desktop | U26: 4 | V26: 4 | W26: 8
A27: 46208.957 | B27: e30b3be204d2fa9d7cc26eec59e7108d | C27: Katrinacarrotss | D27: 0 | E27: 💥 Искорки (ДС 2026q3) | F27: 2 | G27: 1 | H27: 3 | I27: 0 | J27: 5 | K27: -1 | L27: 1 | M27: 4 | N27: 2 | O27: 1 | P27: 4 | Q27: Мне нужно включить в свою жизнь отдых. ежедневный, еженедельный, ежемесячный, ежегодный. Я на правильном пути | R27: Здорово, что есть такой проект и он помогает людям улучшать жизнь | S27: 210 | T27: desktop | U27: 8 | V27: 3 | W27: 13
A28: 46209.336 | B28: 172a6a56331da047b00273e32207d689 | C28: sp190819 | D28: 0 | E28: чат | F28: 2 | G28: 1 | H28: 1 | I28: 2 | J28: 5 | K28: 1 | L28: 0 | M28: 3 | N28: 3 | O28: 1 | P28: 3 | Q28: 1. То, что в списке моих текущих задач практически нет задач, которые напрямую бы вели меня к моим целям, 2. То, что отдых можно и нужно планировать и организовывать как сам отдых, так и время для него... | R28: Вижу большую ценность в практике, вовлечен скорее на минималках, то есть делаю необходимое почти в срок, меня это устраивает... | S28: 331 | T28: desktop | U28: 6 | V28: 4 | W28: 10
A29: 46209.355 | B29: eb27c285c0911029f321c56039b04f93 | C29: mitgych | D29: 0 | E29: 💥 Искорки (ДС 2026q3) | F29: 2 | G29: 2 | H29: 2 | I29: 0 | J29: 4 | K29: 0 | L29: 2 | M29: 3 | N29: 2 | O29: 1 | P29: 3 | Q29: джедайский старт - мой шанс выбраться из рутины. | S29: 48724 | T29: desktop | U29: 6 | V29: 3 | W29: 11
A30: 46209.389 | B30: 5dde0de6f7bf2f7bd95fdcf716c9debe | C30: tigrenok_katiel | D30: 0 | E30: ☀️ Лучики (ДС 2026q3) | F30: 2 | G30: 1 | H30: 2 | I30: 1 | J30: 6 | K30: 3 | L30: 1 | M30: 2 | N30: 3 | O30: 3 | P30: 2 | S30: 88 | T30: desktop | U30: 4 | V30: 6 | W30: 6
A31: 46209.448 | B31: 96ec63d4dab19babc9358e877514b445 | C31: chillimpostor | D31: 0 | E31: ☀️ Лучики (ДС 2026q3) | F31: 2 | G31: 1 | H31: 2 | I31: 1 | J31: 5 | K31: 0 | L31: 2 | M31: 3 | N31: 2 | O31: 2 | P31: 3 | Q31: Главные идеи/выводы по теме недели. - Важно благополучие, работа и дела не цель, а средство. - Самоорганизация и планирование, системы и техники, нужны чтобы жить лучше, а не делать больше. - Отдых и досуг не награда, а забота о себе. Без них нет сил и желания, только истощение, выгорание и саботаж. | S31: 219 | T31: mobile | U31: 6 | V31: 4 | W31: 10
A32: 46209.493 | B32: 995b4fba758836832c8b3c807d0dd941 | C32: dmtszv | D32: 0 | E32: ☀️ Лучики (ДС 2026q3) | F32: 1 | G32: 1 | H32: 2 | I32: 2 | J32: 5 | K32: 0 | L32: 0 | M32: 1 | N32: 3 | O32: 3 | P32: 1 | Q32: Мне необходимо чётко разделять отдых и работу и не жертвовать первым в пользу второго. | R32: Вы мне нравитесь ;) | S32: 360 | T32: mobile | U32: 2 | V32: 6 | W32: 4
A33: 46209.686 | B33: 76818b0bb39c8fde93db3fe7c435c371 | C33: baikova_f | D33: 0 | E33: чат | F33: 1 | G33: 1 | H33: 1 | I33: 3 | J33: 5 | K33: 1 | L33: -3 | M33: 3 | N33: 3 | O33: 1 | P33: 2 | Q33: Я не умею отдыхать. Срочно учиться отдыхать! Искать радости для ежедневного и еженедельного отдыха. | R33: 🫶 | S33: 596 | T33: desktop | U33: 5 | V33: 4 | W33: 9
A34: 46209.914 | B34: 07aa1418f1cf5886048222d19aed58a8 | C34: Ninanikolavna | D34: 0 | E34: 🌟 Звёздочки (ДС 2026q3) | F34: 2 | G34: 2 | H34: 2 | I34: 0 | J34: 6 | K34: 2 | L34: 1 | M34: 3 | N34: 1 | O34: 1 | P34: 2 | Q34: Что отдых в шкале важности должен быть наравне с работой. А не на последнем месте, как у меня. | R34: Спасибо, мне у вас нравится:) | S34: 438 | T34: mobile | U34: 5 | V34: 2 | W34: 11
A35: 46209.964 | B35: 39de27188ff28233cab652101f1324b2 | C35: oNZ7xpXJfrkasyb2enBr | D35: 0 | E35: 🌟 Звёздочки (ДС 2026q3) | F35: 0 | G35: 0 | H35: 2 | I35: 4 | J35: 4 | K35: 1 | L35: -3 | M35: 0 | N35: 3 | O35: 3 | P35: 1 | Q35: Укрепился в мысли, что без качественного целеполагания эффективно тратить мыслетопливо не получится. А для целей нужно сформулировать идентичность. В свою очередь для определения идентичности, чтобы хватило сил, сначала нужно научиться отдыхать (на этой формулировке обезьяну хватил Кондратий). | S35: 656 | T35: desktop | U35: 1 | V35: 6 | W35: 3
A36: 46210.319 | B36: b5d32088b1e337361fdc777e91d56681 | C36: smart_roger | D36: 0 | E36: 🔥 Огоньки (ДС 2026q3) | F36: 2 | G36: 1 | H36: 3 | I36: 0 | J36: 4 | K36: 1 | L36: -1 | M36: 2 | N36: 3 | O36: 2 | P36: 3 | S36: 46 | T36: mobile | U36: 5 | V36: 5 | W36: 8
A37: 46210.333 | B37: 93d360291e11d9552e18d5338e87b754 | C37: zhilabylamasha | D37: 0 | E37: 💥%20Искорки%20(ДС%202026q3) | F37: 1 | G37: 2 | H37: 1 | I37: 2 | J37: 5 | K37: 1 | L37: 1 | M37: 1 | N37: 3 | O37: 4 | P37: 1 | Q37: Если есть время, нужно в него «попадать», иначе потом вернуться к задаче будет сложно. | S37: 98 | T37: mobile | U37: 2 | V37: 7 | W37: 3
A38: 46210.46 | B38: 1abd48cde723ee4585125f117925cfa7 | C38: TaM_tAm_666 | D38: 0 | E38: ☀️ Лучики (ДС 2026q3) | F38: 0 | G38: 1 | H38: 4 | I38: 1 | J38: 5 | K38: 1 | L38: -3 | M38: 1 | N38: 3 | O38: 2 | P38: 1 | Q38: Нужно регулярно ходить в отпуска. Кайфовый отпуск - залог хорошего настроения. | S38: 410 | T38: desktop | U38: 2 | V38: 5 | W38: 5
A39: 46210.482 | B39: e09a43a51e3b97f4d10cd33ed5c51f75 | C39: OlegLyukshin | D39: 0 | E39: ☀️%20Лучики%20(ДС%202026q3) | F39: 3 | G39: 1 | H39: 2 | I39: 0 | J39: 3 | K39: 0 | L39: -1 | M39: 2 | N39: 1 | O39: 2 | P39: 2 | S39: 70 | T39: mobile | U39: 4 | V39: 3 | W39: 9
A40: 46210.515 | B40: 456b8de36dc43a6c82a07736d53d3379 | C40: komalexei | D40: 0 | E40: 💥 Искорки (ДС 2026q3) | F40: 3 | G40: 1 | H40: 2 | I40: 0 | J40: 5 | K40: 1 | L40: 0 | M40: 3 | N40: 3 | O40: 2 | P40: 2 | Q40: Важно находить время для отдыха который тебя порадует или просто отключиться от информационного шума и прогуляться 10-15 минут наедине с самим собой. | S40: 474 | T40: mobile | U40: 5 | V40: 5 | W40: 8
A41: 46210.552 | B41: ca4e5e94257151975f77944f3c317d54 | C41: vkomiko | D41: 0 | E41: 💥%20Искорки%20(ДС%202026q3) | F41: 2 | G41: 2 | H41: 2 | I41: 0 | J41: 4 | K41: 1 | L41: 1 | M41: 3 | N41: 3 | O41: 1 | P41: 4 | Q41: Нам нужен не отдых, а пополнение батарейки. Батарейка может быть пополнена различными активностями, которые тебя драйвят | S41: 166 | T41: mobile | U41: 7 | V41: 4 | W41: 11
A42: 46210.935 | B42: f12da707928e9219547f12ad4873ba06 | C42: M_Gaidamaka | D42: 0 | E42: 🔥%20Огоньки%20(ДС%202026q3) | F42: 1 | G42: 3 | H42: 2 | I42: 0 | J42: 6 | K42: 1 | L42: -1 | M42: 2 | N42: 4 | O42: 3 | P42: 1 | S42: 129 | T42: desktop | U42: 3 | V42: 7 | W42: 4
A43: 46211.175 | B43: 2a55a70f24ab521478717d06e85910a0 | C43: kotofos | D43: 0 | E43: ☀️ Лучики (ДС 2026q3) | F43: 1 | G43: 1 | H43: 3 | I43: 1 | J43: 3 | K43: -1 | L43: -2 | M43: 2 | N43: 3 | O43: 2 | P43: 3 | Q43: Надо отдых системный наладить | S43: 257 | T43: desktop | U43: 5 | V43: 5 | W43: 8
A44: 46211.47 | B44: b1c114aeeb7698f2cedb9d1f3d0e6426 | C44: semarglll | D44: 0 | E44: чат | F44: 5 | G44: 1 | H44: 0 | I44: 0 | J44: 5 | K44: -1 | L44: 2 | M44: 3 | N44: 1 | O44: 1 | P44: 3 | S44: 72406 | T44: desktop | U44: 6 | V44: 2 | W44: 12
A45: 46211.668 | B45: df389724d3ed7d5fe7740d6a4b6ea869 | C45: maximgalson | D45: 0 | E45: 🔥%20Огоньки%20(ДС%202026q3) | F45: 0 | G45: 0 | H45: 6 | I45: 0 | J45: 6 | K45: 0 | L45: -3 | M45: 3 | N45: 2 | O45: 2 | P45: 1 | S45: 74 | T45: desktop | U45: 4 | V45: 4 | W45: 8
A46: 46211.672 | B46: 0f2a70caa95c141428b842dadf0d42ac | C46: GriDV | D46: 0 | E46: 💥 Искорки (ДС 2026q3) | F46: 1 | G46: 2 | H46: 2 | I46: 1 | J46: 6 | K46: 1 | L46: -2 | M46: 3 | N46: 2 | O46: 2 | P46: 1 | S46: 113 | T46: desktop | U46: 4 | V46: 4 | W46: 8
A47: 46211.678 | B47: 8f0e737962cf14494102fe8b5b39e394 | C47: a_a_koles | D47: 0 | E47: 💥%20Искорки%20(ДС%202026q3) | F47: 1 | G47: 1 | H47: 0 | I47: 4 | J47: 1 | K47: -2 | L47: 0 | M47: 4 | N47: 1 | O47: 1 | P47: 3 | S47: 177 | T47: desktop | U47: 7 | V47: 2 | W47: 13
A48: 46211.686 | B48: 907dc9bcbe5375dc7729e268267cf6e8 | C48: katerrna | D48: 0 | E48: 12НГ 2026q3 | F48: 1 | G48: 3 | H48: 2 | I48: 0 | J48: 5 | K48: 1 | L48: 0 | M48: 3 | N48: 3 | O48: 2 | P48: 1 | S48: 70 | T48: mobile | U48: 4 | V48: 5 | W48: 7
A49: 46211.69 | B49: af8def6b37b3addde751b09ae3251fc8 | C49: sersch_serg | D49: 0 | E49: 12НГ 2026q3 | F49: 3 | G49: 1 | H49: 2 | I49: 0 | J49: 5 | K49: 0 | L49: -1 | M49: 3 | N49: 3 | O49: 3 | P49: 1 | S49: 79 | T49: mobile | U49: 4 | V49: 6 | W49: 6
A50: 46211.691 | B50: 91da97b37c23df3ed0caacafa924db34 | C50: moronizzz | D50: 0 | E50: 12НГ 2026q3 | F50: 5 | G50: 1 | H50: 0 | I50: 0 | J50: 1 | K50: 0 | L50: 3 | M50: 0 | N50: 3 | O50: 0 | P50: 0 | S50: 45 | T50: desktop | U50: 0 | V50: 3 | W50: 5
A51: 46211.692 | B51: dd32ff21b543384e43b7c70e5668afd7 | C51: ekandria_nova | D51: 0 | E51: 12НГ%202026q3 | F51: 0 | G51: 1 | H51: 5 | I51: 0 | J51: 5 | K51: -2 | L51: -2 | M51: 2 | N51: 3 | O51: 3 | P51: 2 | S51: 78 | T51: mobile | U51: 4 | V51: 6 | W51: 6
A52: 46211.698 | B52: 3486a175ddce3b22c918448f03119057 | C52: tem_ar | D52: 0 | E52: 12НГ 2026q3 | F52: 1 | G52: 0 | H52: 5 | I52: 0 | J52: 7 | K52: 3 | L52: 0 | M52: 2 | N52: 2 | O52: 2 | P52: 2 | S52: 36 | T52: mobile | U52: 4 | V52: 4 | W52: 8
A53: 46211.705 | B53: 29db108878d08e1af918b7431265ee1e | C53: Vibris | D53: 0 | E53: 12НГ 2026q3 | F53: 2 | G53: 2 | H53: 2 | I53: 0 | J53: 3 | K53: -2 | L53: 0 | M53: 1 | N53: 4 | O53: 1 | P53: 0 | Q53: Страт сессия забрала очень много сил, после этого мог делать только совсем простые дела и гулять. Хотя сознательно не казалось, что мы что-то такое делали. | S53: 1032 | T53: mobile | U53: 1 | V53: 5 | W53: 4
A54: 46211.705 | B54: 8a64118bdf9f0aaec6a5ee9ca450489b | C54: dmtrx7alien | D54: 0 | E54: 12НГ 2026q3 | F54: 0 | G54: 3 | H54: 3 | I54: 0 | J54: 6 | K54: 0 | L54: -2 | M54: 1 | N54: 4 | O54: 3 | P54: 0 | Q54: В сложные моменты жизни, сосредоточенность на выполнение повседневных дел помогает мне уравновешивать психическое состоянии (на основе ежедневного мониторинга) | S54: 294 | T54: mobile | U54: 1 | V54: 7 | W54: 2
A55: 46211.707 | B55: cc56609dd18b7e32d7e07daac57d01f7 | C55: lyuda_polshikova | D55: 0 | E55: 12НГ%202026q3 | F55: 1 | G55: 2 | H55: 3 | I55: 0 | J55: 5 | K55: -1 | L55: 0 | M55: 1 | N55: 3 | O55: 3 | P55: 1 | Q55: Что надо брать достаточно много всяких и разных проектов, чтобы было потом что «убить». | S55: 158 | T55: mobile | U55: 2 | V55: 6 | W55: 4
A56: 46211.724 | B56: 00cd3997352ef95032ff68ad8914c528 | C56: pavlbon | D56: 0 | E56: 12НГ%202026q3 | F56: 6 | G56: 0 | H56: 0 | I56: 0 | J56: 1 | K56: 0 | L56: 3 | M56: 4 | N56: 0 | O56: 1 | P56: 3 | S56: 57 | T56: mobile | U56: 7 | V56: 1 | W56: 14
A57: 46211.731 | B57: c96511e8423a119c502bcaca23880c63 | C57: msartaev | D57: 0 | E57: 12НГ%202026q3 | F57: 2 | G57: 3 | H57: 1 | I57: 0 | J57: 6 | K57: 1 | L57: 0 | M57: 3 | N57: 3 | O57: 2 | P57: 2 | Q57: То что ты умеешь это хрень по важности) как и результаты) а то как ты продаешь это важнее всего остального | S57: 121 | T57: mobile | U57: 5 | V57: 5 | W57: 8
A58: 46211.735 | B58: 0deaf94b0052d254767faae2f6e40deb | C58: ChasM2 | D58: 0 | E58: 12НГ 2026q3 | F58: 0 | G58: 3 | H58: 3 | I58: 0 | J58: 6 | K58: 2 | L58: 0 | M58: 1 | N58: 4 | O58: 3 | P58: 0 | Q58: Сеть больше отдохни ) | S58: 107 | T58: mobile | U58: 1 | V58: 7 | W58: 2
A59: 46211.743 | B59: 3a51e900aad52a1ed1be08ceeefc1428 | C59: graywrk | D59: 0 | E59: 12НГ%202026q3 | F59: 2 | G59: 2 | H59: 2 | I59: 0 | J59: 7 | K59: 2 | L59: 0 | M59: 1 | N59: 3 | O59: 3 | P59: 0 | S59: 4508 | T59: desktop | U59: 1 | V59: 6 | W59: 3
A60: 46211.755 | B60: 3c2825760120919ff1ed8e359710ef8d | C60: MishinaAlena | D60: 0 | E60: чат | F60: 3 | G60: 2 | H60: 1 | I60: 0 | J60: 6 | K60: 2 | L60: 2 | M60: 2 | N60: 3 | O60: 2 | P60: 1 | Q60: 1 минута планки бодрит. Если не заряжать телефон с вечера, то его приходится заряжать утром (а не залипать в него). Я пока не могу справится с перекосом в работу и выжитым лимоном в конце рабочего дня. У меня не бывает проблем со сном, потому что я просто вырубаюсь. | S60: 356 | T60: desktop | U60: 3 | V60: 5 | W60: 6
A61: 46211.76 | B61: ea1143d7a1b09867efc8da7edce1494e | C61: Margarita_Zok | D61: 0 | E61: 12НГ%202026q3 | F61: 2 | G61: 2 | H61: 2 | I61: 0 | J61: 2 | K61: -2 | L61: 2 | M61: 2 | N61: 2 | O61: 2 | P61: 3 | Q61: Лечись! Лечись! Пока не восстановишь тушку - будешь чучелом! | R61: Боюсь, что мои крайне херовые результаты из-за болезни длинной вам поломают метрику | S61: 120 | T61: mobile | U61: 5 | V61: 4 | W61: 9
A62: 46211.785 | B62: eceea811f745cc72f890dbf3a7df18f0 | C62: yana_selezneva_coach | D62: 0 | E62: 12НГ%202026q3 | F62: 1 | G62: 2 | H62: 3 | I62: 0 | J62: 6 | K62: 1 | L62: 0 | M62: 2 | N62: 3 | O62: 3 | P62: 2 | Q62: - | R62: Слишком много вопросов в опросниках | S62: 80 | T62: mobile | U62: 4 | V62: 6 | W62: 6
A63: 46211.817 | B63: 9b1370f288868e2424c9b0945ef973d6 | C63: barvarbar | D63: 0 | E63: 12НГ 2026q3 | F63: 0 | G63: 5 | H63: 1 | I63: 0 | J63: 6 | K63: -2 | L63: 0 | M63: 1 | N63: 4 | O63: 1 | P63: 0 | Q63: Отдых -- великое дело | R63: Опросы заняли вместе совсем не 5 минут 😡 | S63: 271 | T63: desktop | U63: 1 | V63: 5 | W63: 4
A64: 46211.847 | B64: e215541aeeb0c244d191e36b7d7b9ffe | C64: imagicdeer | D64: 0 | E64: ☀️%20Лучики%20(ДС%202026q3) | F64: 2 | G64: 2 | H64: 2 | I64: 0 | J64: 5 | K64: 1 | L64: -2 | M64: 1 | N64: 4 | O64: 3 | P64: 1 | Q64: У меня в окружении есть тёплые важные друзья. Я досточно хорош чтобы двигаться к успеху и быть полезным. Я в целом достачно крут и моя отправная точка достаточно крепкая. | R64: Я сдал отчёт не вовремя😢я вылетел из обучения в отдых и не чекал чатики. Не знал что будет отчёт и это важно. Как увидел сразу заполнил. | S64: 419 | T64: mobile | U64: 2 | V64: 7 | W64: 3
A65: 46211.907 | B65: 6afb080b69ecbb052834b24f9fc809e7 | C65: vasilev_dm | D65: 0 | E65: 12НГ 2026q3 | F65: 3 | G65: 0 | H65: 3 | I65: 0 | J65: 2 | K65: -2 | L65: 0 | M65: 2 | N65: 3 | O65: 2 | P65: 3 | Q65: Научился радоваться простым вещам: поспал, поел, сходил на тренировку - значит все неплохо, несмотря на продолбыши по проектам | S65: 108 | T65: mobile | U65: 5 | V65: 5 | W65: 8
A66: 46211.943 | B66: a8fb2068a5197331612829494ebef43e | C66: tutankhamonych | D66: 0 | E66: 12НГ 2026q3 | F66: 3 | G66: 1 | H66: 2 | I66: 0 | J66: 5 | K66: -1 | L66: 0 | M66: 1 | N66: 3 | O66: 2 | P66: 2 | Q66: Впихиваем не только в день, но и в жизнь. А оно не впихивается. | R66: Опять кубики. Без автоматизации в планировщике - малополезное тыкание. Вопросы же из серии "Давно ли Вы бросили пить коньяк по утрам" | S66: 292 | T66: desktop | U66: 3 | V66: 5 | W66: 6
A67: 46212.03 | B67: 43ddf1704048220f901e7270b14463b8 | C67: mikulaYkt | D67: 0 | E67: 🔥 Огоньки (ДС 2026q3) | F67: 0 | G67: 0 | H67: 3 | I67: 3 | J67: 3 | K67: 0 | L67: 2 | M67: 1 | N67: 3 | O67: 3 | P67: 1 | S67: 64 | T67: desktop | U67: 2 | V67: 6 | W67: 4
A68: 46212.254 | B68: c09b313158d7c99459cf8921bbee3ba9 | C68: nabiev80 | D68: 0 | E68: 12НГ 2026q3 | F68: 1 | G68: 4 | H68: 1 | I68: 0 | J68: 6 | K68: 0 | L68: -1 | M68: 2 | N68: 3 | O68: 4 | P68: 0 | Q68: Сила вопроса чтобы что ! | S68: 846 | T68: mobile | U68: 2 | V68: 7 | W68: 3
A69: 46212.317 | B69: 610d12368c2476aa1df5752be4244644 | C69: nkatsurina | D69: 0 | E69: 12НГ 2026q3 | F69: 1 | G69: 1 | H69: 4 | I69: 0 | J69: 5 | K69: 0 | L69: 0 | M69: 1 | N69: 3 | O69: 3 | P69: 2 | S69: 227 | T69: mobile | U69: 3 | V69: 6 | W69: 5
A70: 46212.382 | B70: 79832b28fea8022ff7de4ba54b0c289a | C70: stargriv | D70: 0 | E70: 12НГ%202026q3 | F70: 0 | G70: 2 | H70: 4 | I70: 0 | J70: 2 | K70: -2 | L70: -3 | M70: 2 | N70: 1 | O70: 1 | P70: 4 | S70: 59 | T70: mobile | U70: 6 | V70: 2 | W70: 12
A71: 46212.39 | B71: 86af4e3349b529826471ce8b722ff946 | C71: tael_taeglin | D71: 0 | E71: 12НГ%202026q3 | F71: 1 | G71: 2 | H71: 3 | I71: 0 | J71: 5 | K71: -1 | L71: 2 | M71: 3 | N71: 2 | O71: 1 | P71: 3 | Q71: Нужно нанимать ещё одного менеджера | S71: 188 | T71: mobile | U71: 6 | V71: 3 | W71: 11
A72: 46212.395 | B72: 6420a53104e9dac75af4a5af3514e71b | C72: Kos_Egor | D72: 0 | E72: 12НГ 2026q3 | F72: 1 | G72: 3 | H72: 2 | I72: 0 | J72: 5 | K72: 2 | L72: 2 | M72: 3 | N72: 3 | O72: 1 | P72: 3 | S72: 63 | T72: desktop | U72: 6 | V72: 4 | W72: 10
A73: 46212.446 | B73: 45ee2b4889ec574f5fc2323f9aec5995 | C73: Phoeneeks | D73: 0 | E73: 12НГ 2026q3 | F73: 3 | G73: 2 | H73: 1 | I73: 0 | J73: 5 | K73: -3 | L73: 1 | M73: 2 | N73: 4 | O73: 3 | P73: 2 | Q73: Свой паттерн, который проявляется в том, что я ко второму спринту подхожу в состоянии, когда база и фундамент в просадке. Перед тем, как достигнуть успеха, я подсознательно делаю действия, которые отдаляют меня от него, и усложняют мне путь к нему. Отсутствие сна в течение нескольких дней перед стратсессией или другим важным мероприятием, которое потенциально увеличит количество задач, проектов, либо будет требовать ответственности от меня. А ещё неумение отдыхать. Ведь только когда "Бобик сдох", мне официально разрешено отдыхать в моей голове. А раз я это вижу и знаю - могу с этим что-то сделать. Собственно в спринте буду над этим работать - большинство проектов как раз об этом всём в этот раз у меня, забота и любовь к себе в действиях, осознаное рукожопие, и беру по минимуму, фокусируясь на фундаменте, кайфах, и основном. Антиуспешныйуспех. Слишком много достигатора необходимо полярным вытравливать. | R73: Ураааа!!! Новый вариант опроса!!!))) Моя любимая психология(скупая слеза потекла от воспоминаний заполнения разных опросников с подобными шкалами)! :) | S73: 743 | T73: desktop | U73: 4 | V73: 7 | W73: 5
A74: 46212.475 | B74: 9894f2b4408713b0f1a8b9011b4e348b | C74: ksemiya | D74: 0 | E74: 12НГ 2026q3 | F74: 1 | G74: 3 | H74: 2 | I74: 0 | J74: 6 | K74: 1 | L74: -1 | M74: 2 | N74: 3 | O74: 3 | P74: 2 | S74: 125 | T74: desktop | U74: 4 | V74: 6 | W74: 6
A75: 46212.578 | B75: 9bdb1a51e8f5f6d34358e0a1e935b1ec | C75: alvlivanov | D75: 0 | E75: 12НГ 2026q3 | F75: 2 | G75: 2 | H75: 2 | I75: 0 | J75: 6 | K75: 0 | L75: -1 | M75: 2 | N75: 3 | O75: 2 | P75: 2 | Q75: Вселенная помогает тебе решать проблемы, только важно сохранять спокойствие и продолжать движение - делать что-то в направлении решения проблем. | S75: 172 | T75: desktop | U75: 4 | V75: 5 | W75: 7
A76: 46212.588 | B76: fb79a2706e0b4fc001b9b10a2d350365 | C76: Nikki2035 | D76: 0 | E76: 12НГ 2026q3 | F76: 1 | G76: 2 | H76: 3 | I76: 0 | J76: 7 | K76: 0 | L76: 0 | M76: 0 | N76: 3 | O76: 4 | P76: 0 | S76: 122 | T76: desktop | U76: 0 | V76: 7 | W76: 1
A77: 46212.603 | B77: d75e36485033a47954f9f9255ac3f7e6 | C77: maksimbochkov | D77: 0 | E77: 12НГ 2026q3 | F77: 1 | G77: 2 | H77: 3 | I77: 0 | J77: 5 | K77: 0 | L77: 0 | M77: 1 | N77: 3 | O77: 3 | P77: 1 | S77: 52 | T77: desktop | U77: 2 | V77: 6 | W77: 4
A78: 46212.61 | B78: 0dae5025e34639ab3929dc122e4f74ab | C78: Mur_Roman | D78: 0 | E78: 12НГ%202026q3 | F78: 2 | G78: 2 | H78: 1 | I78: 1 | J78: 5 | K78: 0 | L78: 1 | M78: 2 | N78: 3 | O78: 2 | P78: 1 | S78: 175 | T78: desktop | U78: 3 | V78: 5 | W78: 6
A79: 46212.995 | B79: e0f732ad647f74734f674a9b2ef834bf | C79: Alexs1288 | D79: 0 | E79: 🔥 Огоньки (ДС 2026q3) | F79: 2 | G79: 1 | H79: 1 | I79: 2 | J79: 5 | K79: 0 | L79: 1 | M79: 1 | N79: 3 | O79: 2 | P79: 2 | S79: 263 | T79: mobile | U79: 3 | V79: 5 | W79: 6
A80: 46213.263 | B80: 68828d1ae802dad3dd30894504d75436 | C80: Olga_zabrodina79 | D80: 0 | E80: 🌟 Звёздочки (ДС 2026q3) | F80: 6 | G80: 0 | H80: 0 | I80: 0 | J80: 2 | K80: -2 | L80: 3 | M80: 4 | N80: 1 | O80: 1 | P80: 4 | Q80: Надо отдыхать. Сон по 3 -4 часа в сутки не способствует продуктивной работе | S80: 196 | T80: mobile | U80: 8 | V80: 2 | W80: 14
A81: 46213.366 | B81: cb4048cd99781619620e1f1137abf668 | C81: basdanil | D81: 0 | E81: 12НГ%202026q3 | F81: 1 | G81: 2 | H81: 1 | I81: 2 | J81: 3 | K81: -2 | L81: -1 | M81: 2 | N81: 3 | O81: 3 | P81: 2 | Q81: Были отгулы, ни могу вернуться в рабочий режим никак | S81: 149 | T81: mobile | U81: 4 | V81: 6 | W81: 6
A82: 46213.418 | B82: 0b8208c9184792ec0951a5cd9516578c | C82: temp_nick | D82: 0 | E82: 12НГ 2026q3 | F82: 0 | G82: 3 | H82: 3 | I82: 0 | J82: 3 | K82: -2 | L82: -2 | M82: 2 | N82: 2 | O82: 2 | P82: 2 | S82: 47 | T82: desktop | U82: 4 | V82: 4 | W82: 8
A83: 46213.533 | B83: 82848daefd958969cff9b08b52699558 | C83: advertumacj | D83: 0 | E83: 12НГ 2026q3 | F83: 1 | G83: 1 | H83: 4 | I83: 0 | J83: 4 | K83: -1 | L83: -1 | M83: 2 | N83: 3 | O83: 3 | P83: 1 | Q83: прикольно, когда попадаются новые заряженные бадди (и самое главное -- случайные) -- сразу будто свежий сахар для дрожжей ума | R83: на 3 день прокрастинации бота я смог заполнить опросник | S83: 126 | T83: desktop | U83: 3 | V83: 6 | W83: 5
A84: 46213.587 | B84: 1b480e3de5c278a24ca4c8f4c195911e | C84: unSaintMan | D84: 0 | E84: 12НГ 2026q3 | F84: 2 | G84: 1 | H84: 3 | I84: 0 | J84: 3 | K84: -1 | L84: 2 | M84: 3 | N84: 2 | O84: 2 | P84: 3 | Q84: Вздох - ты жив не сдох. | R84: Спасибо! | S84: 3550 | T84: desktop | U84: 6 | V84: 4 | W84: 10
A85: 46213.587 | B85: d7e4c894f8bcf8a60528d452b8f8884c | C85: vprgn | D85: 0 | E85: 12НГ%202026q3 | F85: 2 | G85: 2 | H85: 2 | I85: 0 | J85: 6 | K85: 2 | L85: 1 | M85: 1 | N85: 3 | O85: 3 | P85: 2 | S85: 786 | T85: desktop | U85: 3 | V85: 6 | W85: 5
A86: 46213.718 | B86: 417bbf8c9da6b474faaaff9581983237 | C86: Knovelaer | D86: 0 | E86: чат | F86: 2 | G86: 1 | H86: 3 | I86: 0 | J86: 3 | K86: 0 | L86: 1 | M86: 2 | N86: 2 | O86: 2 | P86: 2 | S86: 36 | T86: desktop | U86: 4 | V86: 4 | W86: 8
A87: 46213.765 | B87: de5cdeaa1c929650105aa3ee03ea02b2 | C87: Alexey_Logic | D87: 0 | E87: 🔥 Огоньки (ДС 2026q3) | F87: 2 | G87: 2 | H87: 2 | I87: 0 | J87: 4 | K87: 2 | L87: -2 | M87: 1 | N87: 3 | O87: 3 | P87: 1 | Q87: Нужно больше времени уделять восстановлению | R87: Вы классные) | S87: 136 | T87: desktop | U87: 2 | V87: 6 | W87: 4
A88: 46214.579 | B88: 26ae4319ab36030802a133134df0e1b8 | C88: MagicUnderHood | D88: 0 | E88: 12НГ 2026q3 | F88: 2 | G88: 1 | H88: 2 | I88: 1 | J88: 7 | K88: -1 | L88: -1 | M88: 3 | N88: 2 | O88: 2 | P88: 2 | S88: 645 | T88: desktop | U88: 5 | V88: 4 | W88: 9
A89: 46214.704 | B89: 196afd81b065be9bf6d545550567568b | C89: irina_katenina | D89: 0 | E89: 12НГ 2026q3 | F89: 2 | G89: 2 | H89: 2 | I89: 0 | J89: 6 | K89: 2 | L89: 2 | M89: 1 | N89: 3 | O89: 3 | P89: 1 | S89: 86 | T89: desktop | U89: 2 | V89: 6 | W89: 4
A90: 46214.779 | B90: 2d7e10af6ccdc3354c7ea9d492c586fa | C90: ChasM2 | D90: 0 | E90: чат | F90: 1 | G90: 2 | H90: 3 | I90: 0 | J90: 5 | K90: 0 | L90: 1 | M90: 1 | N90: 4 | O90: 4 | P90: 0 | S90: 109 | T90: desktop | U90: 1 | V90: 8 | W90: 1
A91: 46214.793 | B91: bd60adaf997d3ac32feae48e906adaae | C91: JohnLP | D91: 0 | E91: 12НГ%202026q3 | F91: 2 | G91: 2 | H91: 1 | I91: 1 | J91: 5 | K91: -1 | L91: -1 | M91: 3 | N91: 3 | O91: 2 | P91: 0 | Q91: 1. Что нужно сократить число проектов на спринт 2. Большинство проектов на спринт - это этапы Больших долгосрочных проектов. | S91: 253 | T91: mobile | U91: 3 | V91: 5 | W91: 6
A92: 46215.367 | B92: 07565f3832674fa410319c2957790fd3 | C92: nvkoy | D92: 1 | E92: 🌟 Звёздочки (ДС 2026q3) | F92: 0 | G92: 4 | H92: 2 | I92: 0 | J92: 5 | K92: 2 | L92: -2 | M92: 2 | N92: 4 | O92: 3 | P92: 0 | S92: 102 | T92: desktop | U92: 2 | V92: 7 | W92: 3
A93: 46215.371 | B93: 3ff7142267c4b34e844bc1547210031e | C93: EkaterinaKazmina | D93: 1 | E93: 12НГ 2026q3 | F93: 1 | G93: 2 | H93: 3 | I93: 0 | J93: 3 | K93: 0 | L93: -2 | M93: 2 | N93: 2 | O93: 2 | P93: 2 | S93: 58 | T93: mobile | U93: 4 | V93: 4 | W93: 8
A94: 46215.376 | B94: 95ab724fc6c3cb0f81382017498cc4c8 | C94: anna_metel87 | D94: 1 | E94: 🔥 Огоньки (ДС 2026q3) | F94: 4 | G94: 1 | H94: 1 | I94: 0 | J94: 6 | K94: 3 | L94: 0 | M94: 1 | N94: 4 | O94: 3 | P94: 0 | S94: 635 | T94: mobile | U94: 1 | V94: 7 | W94: 2
A95: 46215.376 | B95: bab98eb7f7465857677c3bc92ba01b5d | C95: popovichse | D95: 1 | E95: 12НГ 2026q3 | F95: 3 | G95: 0 | H95: 3 | I95: 0 | J95: 2 | K95: -2 | L95: 3 | M95: 3 | N95: 1 | O95: 1 | P95: 3 | S95: 72 | T95: mobile | U95: 6 | V95: 2 | W95: 12
A96: 46215.391 | B96: 69b1713d685208eb00216a9ab14718a0 | C96: sersch_serg | D96: 1 | E96: 12НГ 2026q3 | F96: 2 | G96: 2 | H96: 2 | I96: 0 | J96: 6 | K96: 0 | L96: -1 | M96: 1 | N96: 3 | O96: 3 | P96: 1 | S96: 54 | T96: mobile | U96: 2 | V96: 6 | W96: 4
A97: 46215.391 | B97: 048f1daccc309f980024b9de2ebdb972 | C97: kiralary | D97: 1 | E97: ☀️%20Лучики%20(ДС%202026q3) | F97: 2 | G97: 3 | H97: 1 | I97: 0 | J97: 6 | K97: 3 | L97: 2 | M97: 2 | N97: 3 | O97: 3 | P97: 3 | Q97: Многие мои проблемы с перегруженностью были от невыписанных задач. Я столько всего выписала после практики крючками, и стало гораздо легче жить | R97: Спасибо большое за ваш курс! Это какое-то чудо! | S97: 325 | T97: mobile | U97: 5 | V97: 6 | W97: 7
A98: 46215.393 | B98: 41b69a17b112b1d8528da06773356f11 | C98: shaklein_e | D98: 1 | E98: 🔥%20Огоньки%20(ДС%202026q3) | F98: 1 | G98: 4 | H98: 1 | I98: 0 | J98: 6 | K98: 0 | L98: 0 | M98: 1 | N98: 3 | O98: 4 | P98: 1 | S98: 103 | T98: mobile | U98: 2 | V98: 7 | W98: 3
A99: 46215.4 | B99: 1db034b5a4f4931ff05cbbf2e24bcc95 | C99: maximvj | D99: 1 | E99: 12НГ%202026q3 | F99: 4 | G99: 0 | H99: 0 | I99: 2 | J99: 3 | K99: -2 | L99: 1 | M99: 3 | N99: 3 | O99: 3 | P99: 2 | S99: 82 | T99: desktop | U99: 5 | V99: 6 | W99: 7
A100: 46215.409 | B100: 68f696faba6516465a6a0b113f7500e6 | C100: GriDV | D100: 1 | E100: 💥 Искорки (ДС 2026q3) | F100: 1 | G100: 1 | H100: 2 | I100: 2 | J100: 5 | K100: 2 | L100: -2 | M100: 2 | N100: 2 | O100: 3 | P100: 0 | S100: 183 | T100: desktop | U100: 2 | V100: 5 | W100: 5
...

Sheet Аналитика
A1: Номер недели | B1: 8 | C1: =COUNTIF(RawData!D:D,CurSprint) -> 19
A3: Корреляции | B3: красное | C3: зеленое | D3: серое | E3: остаток | F3: Удовлетворенность неделей | G3: Похожесть недели | H3: Работа / личная жизнь
A4: Стресс | B4: =CORREL(RawData!F:F,RawData!$W:$W) -> 0.29999389 | C4: =CORREL(RawData!G:G,RawData!$W:$W) -> -0.38973709 | D4: =CORREL(RawData!H:H,RawData!$W:$W) -> -0.01280964 | E4: =CORREL(RawData!I:I,RawData!$W:$W) -> 0.076878179 | F4: =CORREL(RawData!J:J,RawData!$W:$W) -> -0.4602701 | G4: =CORREL(RawData!K:K,RawData!$W:$W) -> -0.3233229 | H4: =CORREL(RawData!L:L,RawData!$W:$W) -> 0.22043054
A5: Дистресс | B5: =CORREL(RawData!F:F,RawData!$U:$U) -> 0.24188091 | C5: =CORREL(RawData!G:G,RawData!$U:$U) -> -0.31804272 | D5: =CORREL(RawData!H:H,RawData!$U:$U) -> -0.021217448 | E5: =CORREL(RawData!I:I,RawData!$U:$U) -> 0.077723984 | F5: =CORREL(RawData!J:J,RawData!$U:$U) -> -0.34412419 | G5: =CORREL(RawData!K:K,RawData!$U:$U) -> -0.25267316 | H5: =CORREL(RawData!L:L,RawData!$U:$U) -> 0.19483804
A6: Совладание | B6: =CORREL(RawData!F:F,RawData!$V:$V) -> -0.29082283 | C6: =CORREL(RawData!G:G,RawData!$V:$V) -> 0.37332116 | D6: =CORREL(RawData!H:H,RawData!$V:$V) -> -0.00047036845 | E6: =CORREL(RawData!I:I,RawData!$V:$V) -> -0.055900339 | F6: =CORREL(RawData!J:J,RawData!$V:$V) -> 0.47813878 | G6: =CORREL(RawData!K:K,RawData!$V:$V) -> 0.32292825 | H6: =CORREL(RawData!L:L,RawData!$V:$V) -> -0.19344292
A7: Удовлетворенность неделей | B7: =CORREL(RawData!F:F,RawData!J:J) -> -0.25141069 | C7: =CORREL(RawData!G:G,RawData!J:J) -> 0.46529536
A10: Всего ответов | B10: =COUNTIF(RawData!D:D,B1) -> 19
B11: Красное | C11: Зеленое | D11: Серое
A12: 0 | B12: =COUNTIFS(RawData!F:F,$A12,RawData!$D:$D,$B$1)/TotalWeekRespondents -> 0.21052632 | C12: =COUNTIFS(RawData!G:G,$A12,RawData!$D:$D,$B$1)/TotalWeekRespondents -> 0.15789474 | D12: =COUNTIFS(RawData!H:H,$A12,RawData!$D:$D,$B$1)/TotalWeekRespondents -> 0.15789474
A13: 1 | B13: =COUNTIFS(RawData!F:F,$A13,RawData!$D:$D,$B$1)/TotalWeekRespondents -> 0.36842105 | C13: =COUNTIFS(RawData!G:G,$A13,RawData!$D:$D,$B$1)/TotalWeekRespondents -> 0.31578947 | D13: =COUNTIFS(RawData!H:H,$A13,RawData!$D:$D,$B$1)/TotalWeekRespondents -> 0.10526316
A14: 2 | B14: =COUNTIFS(RawData!F:F,$A14,RawData!$D:$D,$B$1)/TotalWeekRespondents -> 0.21052632 | C14: =COUNTIFS(RawData!G:G,$A14,RawData!$D:$D,$B$1)/TotalWeekRespondents -> 0.21052632 | D14: =COUNTIFS(RawData!H:H,$A14,RawData!$D:$D,$B$1)/TotalWeekRespondents -> 0.36842105
A15: 3 | B15: =COUNTIFS(RawData!F:F,$A15,RawData!$D:$D,$B$1)/TotalWeekRespondents -> 0.10526316 | C15: =COUNTIFS(RawData!G:G,$A15,RawData!$D:$D,$B$1)/TotalWeekRespondents -> 0.21052632 | D15: =COUNTIFS(RawData!H:H,$A15,RawData!$D:$D,$B$1)/TotalWeekRespondents -> 0.31578947
A16: 4 | B16: =COUNTIFS(RawData!F:F,$A16,RawData!$D:$D,$B$1)/TotalWeekRespondents -> 0 | C16: =COUNTIFS(RawData!G:G,$A16,RawData!$D:$D,$B$1)/TotalWeekRespondents -> 0.10526316 | D16: =COUNTIFS(RawData!H:H,$A16,RawData!$D:$D,$B$1)/TotalWeekRespondents -> 0
A17: 5 | B17: =COUNTIFS(RawData!F:F,$A17,RawData!$D:$D,$B$1)/TotalWeekRespondents -> 0 | C17: =COUNTIFS(RawData!G:G,$A17,RawData!$D:$D,$B$1)/TotalWeekRespondents -> 0 | D17: =COUNTIFS(RawData!H:H,$A17,RawData!$D:$D,$B$1)/TotalWeekRespondents -> 0
A18: 6 | B18: =COUNTIFS(RawData!F:F,$A18,RawData!$D:$D,$B$1)/TotalWeekRespondents -> 0.10526316 | C18: =COUNTIFS(RawData!G:G,$A18,RawData!$D:$D,$B$1)/TotalWeekRespondents -> 0 | D18: =COUNTIFS(RawData!H:H,$A18,RawData!$D:$D,$B$1)/TotalWeekRespondents -> 0.052631579
B21: Репрезентативность недели
A22: -3 | B22: Значительно хуже | C22: =COUNTIFS(RawData!K:K,A22,RawData!$D:$D,$B$1)/TotalWeekRespondents -> 0.052631579
A23: -2 | B23: Хуже | C23: =COUNTIFS(RawData!K:K,A23,RawData!$D:$D,$B$1)/TotalWeekRespondents -> 0.10526316
A24: -1 | B24: Чуть хуже | C24: =COUNTIFS(RawData!K:K,A24,RawData!$D:$D,$B$1)/TotalWeekRespondents -> 0.21052632
A25: 0 | B25: Как обычно | C25: =COUNTIFS(RawData!K:K,A25,RawData!$D:$D,$B$1)/TotalWeekRespondents -> 0.21052632
A26: 1 | B26: Чуть лучше | C26: =COUNTIFS(RawData!K:K,A26,RawData!$D:$D,$B$1)/TotalWeekRespondents -> 0.26315789
A27: 2 | B27: Лучше | C27: =COUNTIFS(RawData!K:K,A27,RawData!$D:$D,$B$1)/TotalWeekRespondents -> 0.15789474
A28: 3 | B28: Значительно лучше | C28: =COUNTIFS(RawData!K:K,A28,RawData!$D:$D,$B$1)/TotalWeekRespondents -> 0
B30: Личная жизнь или работа
A31: -3 | B31: Всё на личное | C31: =COUNTIFS(RawData!L:L,A31,RawData!$D:$D,$B$1)/TotalWeekRespondents -> 0.052631579
A32: -2 | C32: =COUNTIFS(RawData!L:L,A32,RawData!$D:$D,$B$1)/TotalWeekRespondents -> 0.052631579
A33: -1 | C33: =COUNTIFS(RawData!L:L,A33,RawData!$D:$D,$B$1)/TotalWeekRespondents -> 0.15789474
A34: 0 | B34: Баланс | C34: =COUNTIFS(RawData!L:L,A34,RawData!$D:$D,$B$1)/TotalWeekRespondents -> 0.26315789
A35: 1 | C35: =COUNTIFS(RawData!L:L,A35,RawData!$D:$D,$B$1)/TotalWeekRespondents -> 0.21052632
A36: 2 | C36: =COUNTIFS(RawData!L:L,A36,RawData!$D:$D,$B$1)/TotalWeekRespondents -> 0.10526316
A37: 3 | B37: Всё на работу | C37: =COUNTIFS(RawData!L:L,A37,RawData!$D:$D,$B$1)/TotalWeekRespondents -> 0.15789474
B40: На сколько я доволен неделей?
A41: 1 | B41: Фу, отстой :-( | C41: =COUNTIFS(RawData!J:J,A41,RawData!$D:$D,$B$1)/TotalWeekRespondents -> 0.052631579
A42: 2 | C42: =COUNTIFS(RawData!J:J,A42,RawData!$D:$D,$B$1)/TotalWeekRespondents -> 0.10526316
A43: 3 | C43: =COUNTIFS(RawData!J:J,A43,RawData!$D:$D,$B$1)/TotalWeekRespondents -> 0.15789474
A44: 4 | B44: Средненько | C44: =COUNTIFS(RawData!J:J,A44,RawData!$D:$D,$B$1)/TotalWeekRespondents -> 0.21052632
A45: 5 | C45: =COUNTIFS(RawData!J:J,A45,RawData!$D:$D,$B$1)/TotalWeekRespondents -> 0.21052632
A46: 6 | C46: =COUNTIFS(RawData!J:J,A46,RawData!$D:$D,$B$1)/TotalWeekRespondents -> 0.21052632
A47: 7 | B47: Я - молодец!!1 | C47: =COUNTIFS(RawData!J:J,A47,RawData!$D:$D,$B$1)/TotalWeekRespondents -> 0.052631579
B49: 0 | C49: 1 | D49: 2 | E49: 3 | F49: 4 | G49: 5 | H49: 6 | I49: 7 | J49: 8 | K49: 9 | L49: 10 | M49: 11 | N49: 12
A50: 12НГ | B50: =COUNTIFS(RawData!$E:$E,"*" & $A50 & "*",RawData!$D:$D,B$49) -> 36 | C50: =COUNTIFS(RawData!$E:$E,"*" & $A50 & "*",RawData!$D:$D,C$49) -> 44 | D50: =COUNTIFS(RawData!$E:$E,"*" & $A50 & "*",RawData!$D:$D,D$49) -> 47 | E50: =COUNTIFS(RawData!$E:$E,"*" & $A50 & "*",RawData!$D:$D,E$49) -> 45 | F50: =COUNTIFS(RawData!$E:$E,"*" & $A50 & "*",RawData!$D:$D,F$49) -> 43 | G50: =COUNTIFS(RawData!$E:$E,"*" & $A50 & "*",RawData!$D:$D,G$49) -> 34 | H50: =COUNTIFS(RawData!$E:$E,"*" & $A50 & "*",RawData!$D:$D,H$49) -> 40 | I50: =COUNTIFS(RawData!$E:$E,"*" & $A50 & "*",RawData!$D:$D,I$49) -> 40 | ... N50: =COUNTIFS(RawData!$E:$E,"*" & $A50 & "*",RawData!$D:$D,N$49) -> 0
A51: Звёздочки | B51: =COUNTIFS(RawData!$E:$E,"*" & $A51 & "*",RawData!$D:$D,B$49) -> 10 | C51: =COUNTIFS(RawData!$E:$E,"*" & $A51 & "*",RawData!$D:$D,C$49) -> 12 | D51: =COUNTIFS(RawData!$E:$E,"*" & $A51 & "*",RawData!$D:$D,D$49) -> 10 | E51: =COUNTIFS(RawData!$E:$E,"*" & $A51 & "*",RawData!$D:$D,E$49) -> 9 | F51: =COUNTIFS(RawData!$E:$E,"*" & $A51 & "*",RawData!$D:$D,F$49) -> 5 | G51: =COUNTIFS(RawData!$E:$E,"*" & $A51 & "*",RawData!$D:$D,G$49) -> 4 | H51: =COUNTIFS(RawData!$E:$E,"*" & $A51 & "*",RawData!$D:$D,H$49) -> 3 | I51: =COUNTIFS(RawData!$E:$E,"*" & $A51 & "*",RawData!$D:$D,I$49) -> 6 | ... N51: =COUNTIFS(RawData!$E:$E,"*" & $A51 & "*",RawData!$D:$D,N$49) -> 0
A52: Искорки | B52: =COUNTIFS(RawData!$E:$E,"*" & $A52 & "*",RawData!$D:$D,B$49) -> 13 | C52: =COUNTIFS(RawData!$E:$E,"*" & $A52 & "*",RawData!$D:$D,C$49) -> 9 | D52: =COUNTIFS(RawData!$E:$E,"*" & $A52 & "*",RawData!$D:$D,D$49) -> 13 | E52: =COUNTIFS(RawData!$E:$E,"*" & $A52 & "*",RawData!$D:$D,E$49) -> 7 | F52: =COUNTIFS(RawData!$E:$E,"*" & $A52 & "*",RawData!$D:$D,F$49) -> 7 | G52: =COUNTIFS(RawData!$E:$E,"*" & $A52 & "*",RawData!$D:$D,G$49) -> 3 | H52: =COUNTIFS(RawData!$E:$E,"*" & $A52 & "*",RawData!$D:$D,H$49) -> 5 | I52: =COUNTIFS(RawData!$E:$E,"*" & $A52 & "*",RawData!$D:$D,I$49) -> 3 | ... N52: =COUNTIFS(RawData!$E:$E,"*" & $A52 & "*",RawData!$D:$D,N$49) -> 0
A53: Лучики | B53: =COUNTIFS(RawData!$E:$E,"*" & $A53 & "*",RawData!$D:$D,B$49) -> 13 | C53: =COUNTIFS(RawData!$E:$E,"*" & $A53 & "*",RawData!$D:$D,C$49) -> 10 | D53: =COUNTIFS(RawData!$E:$E,"*" & $A53 & "*",RawData!$D:$D,D$49) -> 11 | E53: =COUNTIFS(RawData!$E:$E,"*" & $A53 & "*",RawData!$D:$D,E$49) -> 10 | F53: =COUNTIFS(RawData!$E:$E,"*" & $A53 & "*",RawData!$D:$D,F$49) -> 8 | G53: =COUNTIFS(RawData!$E:$E,"*" & $A53 & "*",RawData!$D:$D,G$49) -> 9 | H53: =COUNTIFS(RawData!$E:$E,"*" & $A53 & "*",RawData!$D:$D,H$49) -> 6 | I53: =COUNTIFS(RawData!$E:$E,"*" & $A53 & "*",RawData!$D:$D,I$49) -> 7 | ... N53: =COUNTIFS(RawData!$E:$E,"*" & $A53 & "*",RawData!$D:$D,N$49) -> 0
A54: Огоньки | B54: =COUNTIFS(RawData!$E:$E,"*" & $A54 & "*",RawData!$D:$D,B$49) -> 11 | C54: =COUNTIFS(RawData!$E:$E,"*" & $A54 & "*",RawData!$D:$D,C$49) -> 9 | D54: =COUNTIFS(RawData!$E:$E,"*" & $A54 & "*",RawData!$D:$D,D$49) -> 5 | E54: =COUNTIFS(RawData!$E:$E,"*" & $A54 & "*",RawData!$D:$D,E$49) -> 5 | F54: =COUNTIFS(RawData!$E:$E,"*" & $A54 & "*",RawData!$D:$D,F$49) -> 5 | G54: =COUNTIFS(RawData!$E:$E,"*" & $A54 & "*",RawData!$D:$D,G$49) -> 4 | H54: =COUNTIFS(RawData!$E:$E,"*" & $A54 & "*",RawData!$D:$D,H$49) -> 3 | I54: =COUNTIFS(RawData!$E:$E,"*" & $A54 & "*",RawData!$D:$D,I$49) -> 2 | ... N54: =COUNTIFS(RawData!$E:$E,"*" & $A54 & "*",RawData!$D:$D,N$49) -> 0
B57: Неделя 0 | C57: Неделя 1 | D57: Неделя 2 | E57: Неделя 3 | F57: Неделя 4 | G57: Неделя 5 | H57: Неделя 6 | I57: Неделя 7 | J57: Неделя 8 | K57: Неделя 9 | L57: Неделя 10 | M57: Неделя 11 | N57: Неделя 12
A58: 12НГ | B58: =B50/MAX($B50:$K50) -> 0.76595745 | C58: =C50/MAX($B50:$K50) -> 0.93617021 | D58: =D50/MAX($B50:$K50) -> 1 | E58: =E50/MAX($B50:$K50) -> 0.95744681 | F58: =F50/MAX($B50:$K50) -> 0.91489362 | G58: =G50/MAX($B50:$K50) -> 0.72340426 | H58: =H50/MAX($B50:$K50) -> 0.85106383 | I58: =I50/MAX($B50:$K50) -> 0.85106383 | ... N58: =N50/MAX($B50:$K50) -> 0
A59: Звёздочки | B59: =B51/MAX($B51:$K51) -> 0.83333333 | C59: =C51/MAX($B51:$K51) -> 1 | D59: =D51/MAX($B51:$K51) -> 0.83333333 | E59: =E51/MAX($B51:$K51) -> 0.75 | F59: =F51/MAX($B51:$K51) -> 0.41666667 | G59: =G51/MAX($B51:$K51) -> 0.33333333 | H59: =H51/MAX($B51:$K51) -> 0.25 | I59: =I51/MAX($B51:$K51) -> 0.5 | ... N59: =N51/MAX($B51:$K51) -> 0
A60: Искорки | B60: =B52/MAX($B52:$K52) -> 1 | C60: =C52/MAX($B52:$K52) -> 0.69230769 | D60: =D52/MAX($B52:$K52) -> 1 | E60: =E52/MAX($B52:$K52) -> 0.53846154 | F60: =F52/MAX($B52:$K52) -> 0.53846154 | G60: =G52/MAX($B52:$K52) -> 0.23076923 | H60: =H52/MAX($B52:$K52) -> 0.38461538 | I60: =I52/MAX($B52:$K52) -> 0.23076923 | ... N60: =N52/MAX($B52:$K52) -> 0
A61: Лучики | B61: =B53/MAX($B53:$K53) -> 1 | C61: =C53/MAX($B53:$K53) -> 0.76923077 | D61: =D53/MAX($B53:$K53) -> 0.84615385 | E61: =E53/MAX($B53:$K53) -> 0.76923077 | F61: =F53/MAX($B53:$K53) -> 0.61538462 | G61: =G53/MAX($B53:$K53) -> 0.69230769 | H61: =H53/MAX($B53:$K53) -> 0.46153846 | I61: =I53/MAX($B53:$K53) -> 0.53846154 | ... N61: =N53/MAX($B53:$K53) -> 0
A62: Огоньки | B62: =B54/MAX($B54:$K54) -> 1 | C62: =C54/MAX($B54:$K54) -> 0.81818182 | D62: =D54/MAX($B54:$K54) -> 0.45454545 | E62: =E54/MAX($B54:$K54) -> 0.45454545 | F62: =F54/MAX($B54:$K54) -> 0.45454545 | G62: =G54/MAX($B54:$K54) -> 0.36363636 | H62: =H54/MAX($B54:$K54) -> 0.27272727 | I62: =I54/MAX($B54:$K54) -> 0.18181818 | ... N62: =N54/MAX($B54:$K54) -> 0
B65: 1 | C65: 2 | D65: 3 | E65: 4 | F65: 5 | G65: 6 | H65: 7 | I65: 8 | J65: 9 | K65: 10
A66: Всего красного | B66: =SUMIF(RawData!$D:$D,B65,RawData!$F:$F) -> 150 | C66: =SUMIF(RawData!$D:$D,C65,RawData!$F:$F) -> 144 | D66: =SUMIF(RawData!$D:$D,D65,RawData!$F:$F) -> 149 | E66: =SUMIF(RawData!$D:$D,E65,RawData!$F:$F) -> 121 | F66: =SUMIF(RawData!$D:$D,F65,RawData!$F:$F) -> 90 | G66: =SUMIF(RawData!$D:$D,G65,RawData!$F:$F) -> 102 | H66: =SUMIF(RawData!$D:$D,H65,RawData!$F:$F) -> 103 | I66: =SUMIF(RawData!$D:$D,I65,RawData!$F:$F) -> 33 | ... K66: =SUMIF(RawData!$D:$D,K65,RawData!$F:$F) -> 0
A67: Всего зеленого | B67: =SUMIF(RawData!$D:$D,B65,RawData!$G:$G) -> 165 | C67: =SUMIF(RawData!$D:$D,C65,RawData!$G:$G) -> 190 | D67: =SUMIF(RawData!$D:$D,D65,RawData!$G:$G) -> 155 | E67: =SUMIF(RawData!$D:$D,E65,RawData!$G:$G) -> 129 | F67: =SUMIF(RawData!$D:$D,F65,RawData!$G:$G) -> 113 | G67: =SUMIF(RawData!$D:$D,G65,RawData!$G:$G) -> 114 | H67: =SUMIF(RawData!$D:$D,H65,RawData!$G:$G) -> 100 | I67: =SUMIF(RawData!$D:$D,I65,RawData!$G:$G) -> 34 | ... K67: =SUMIF(RawData!$D:$D,K65,RawData!$G:$G) -> 0
B68: =B67/B66 -> 1.1 | C68: =C67/C66 -> 1.3194444 | D68: =D67/D66 -> 1.0402685 | E68: =E67/E66 -> 1.0661157 | F68: =F67/F66 -> 1.2555556 | G68: =G67/G66 -> 1.1176471 | H68: =H67/H66 -> 0.97087379 | I68: =I67/I66 -> 1.030303 | ... K68: =K67/K66 -> #DIV/0!
A70: Средний баланс работа / личное | B70: =SUMIF(RawData!$D:$D,B65,RawData!$L:$L)/COUNTIF(RawData!$D:$D,B65) -> -0.031578947 | C70: =SUMIF(RawData!$D:$D,C65,RawData!$L:$L)/COUNTIF(RawData!$D:$D,C65) -> -0.21052632 | D70: =SUMIF(RawData!$D:$D,D65,RawData!$L:$L)/COUNTIF(RawData!$D:$D,D65) -> -0.28735632 | E70: =SUMIF(RawData!$D:$D,E65,RawData!$L:$L)/COUNTIF(RawData!$D:$D,E65) -> -0.24657534 | F70: =SUMIF(RawData!$D:$D,F65,RawData!$L:$L)/COUNTIF(RawData!$D:$D,F65) -> 0.06779661 | G70: =SUMIF(RawData!$D:$D,G65,RawData!$L:$L)/COUNTIF(RawData!$D:$D,G65) -> -0.23728814 | H70: =SUMIF(RawData!$D:$D,H65,RawData!$L:$L)/COUNTIF(RawData!$D:$D,H65) -> -0.16129032 | I70: =SUMIF(RawData!$D:$D,I65,RawData!$L:$L)/COUNTIF(RawData!$D:$D,I65) -> 0.47368421 | ... K70: =SUMIF(RawData!$D:$D,K65,RawData!$L:$L)/COUNTIF(RawData!$D:$D,K65) -> #DIV/0!
C75: Индекс трудоголизма | D75: Индекс похожести недели | E75: Индекс удовлетворенности неделей | F75: Среднее зеленое | G75: Среднее красное | H75: Среднее серое | I75: Человек с балансом работа / личное
A76: 0 | B76: Неделя 0 | C76: =IF(COUNTIF(RawData!$D:$D,$A76) > 0, (SUMIF(RawData!$D:$D,$A76,RawData!$L:$L)/COUNTIF(RawData!$D:$D,$A76))/3,"") -> 0.047101449 | D76: =IF(COUNTIF(RawData!$D:$D,$A76) > 0, (SUMIF(RawData!$D:$D,$A76,RawData!$K:$K)/COUNTIF(RawData!$D:$D,$A76))/3,"") -> 0.047101449 | E76: =IF(COUNTIF(RawData!$D:$D,$A76) > 0, (SUMIF(RawData!$D:$D,$A76,RawData!$J:$J)/COUNTIF(RawData!$D:$D,$A76))/6,"") -> 0.77536232 | F76: =IF(COUNTIF(RawData!$D:$D,$A76) > 0, (SUMIF(RawData!$D:$D,$A76,RawData!$G:$G)/COUNTIF(RawData!$D:$D,$A76))/6,"") -> 0.26268116 | G76: =IF(COUNTIF(RawData!$D:$D,$A76) > 0, (SUMIF(RawData!$D:$D,$A76,RawData!$F:$F)/COUNTIF(RawData!$D:$D,$A76))/6,"") -> 0.29347826 | H76: =IF(COUNTIF(RawData!$D:$D,$A76) > 0, (SUMIF(RawData!$D:$D,$A76,RawData!$H:$H)/COUNTIF(RawData!$D:$D,$A76))/6,"") -> 0.33695652 | I76: =IF(COUNTIF(RawData!$D:$D,$A76) > 0, (COUNTIFS(RawData!$D:$D,$A76,RawData!L:L,0)/COUNTIF(RawData!$D:$D,$A76)),"") -> 0.27173913
A77: 1 | B77: Неделя 1 | C77: =IF(COUNTIF(RawData!$D:$D,$A77) > 0, (SUMIF(RawData!$D:$D,$A77,RawData!$L:$L)/COUNTIF(RawData!$D:$D,$A77))/3,"") -> -0.010526316 | D77: =IF(COUNTIF(RawData!$D:$D,$A77) > 0, (SUMIF(RawData!$D:$D,$A77,RawData!$K:$K)/COUNTIF(RawData!$D:$D,$A77))/3,"") -> 0.14385965 | E77: =IF(COUNTIF(RawData!$D:$D,$A77) > 0, (SUMIF(RawData!$D:$D,$A77,RawData!$J:$J)/COUNTIF(RawData!$D:$D,$A77))/6,"") -> 0.77894737 | F77: =IF(COUNTIF(RawData!$D:$D,$A77) > 0, (SUMIF(RawData!$D:$D,$A77,RawData!$G:$G)/COUNTIF(RawData!$D:$D,$A77))/6,"") -> 0.28947368 | G77: =IF(COUNTIF(RawData!$D:$D,$A77) > 0, (SUMIF(RawData!$D:$D,$A77,RawData!$F:$F)/COUNTIF(RawData!$D:$D,$A77))/6,"") -> 0.26315789 | H77: =IF(COUNTIF(RawData!$D:$D,$A77) > 0, (SUMIF(RawData!$D:$D,$A77,RawData!$H:$H)/COUNTIF(RawData!$D:$D,$A77))/6,"") -> 0.36315789 | I77: =IF(COUNTIF(RawData!$D:$D,$A77) > 0, (COUNTIFS(RawData!$D:$D,$A77,RawData!L:L,0)/COUNTIF(RawData!$D:$D,$A77)),"") -> 0.23157895
A78: 2 | B78: Неделя 2 | C78: =IF(COUNTIF(RawData!$D:$D,$A78) > 0, (SUMIF(RawData!$D:$D,$A78,RawData!$L:$L)/COUNTIF(RawData!$D:$D,$A78))/3,"") -> -0.070175439 | D78: =IF(COUNTIF(RawData!$D:$D,$A78) > 0, (SUMIF(RawData!$D:$D,$A78,RawData!$K:$K)/COUNTIF(RawData!$D:$D,$A78))/3,"") -> 0.080701754 | E78: =IF(COUNTIF(RawData!$D:$D,$A78) > 0, (SUMIF(RawData!$D:$D,$A78,RawData!$J:$J)/COUNTIF(RawData!$D:$D,$A78))/6,"") -> 0.77719298 | F78: =IF(COUNTIF(RawData!$D:$D,$A78) > 0, (SUMIF(RawData!$D:$D,$A78,RawData!$G:$G)/COUNTIF(RawData!$D:$D,$A78))/6,"") -> 0.33333333 | G78: =IF(COUNTIF(RawData!$D:$D,$A78) > 0, (SUMIF(RawData!$D:$D,$A78,RawData!$F:$F)/COUNTIF(RawData!$D:$D,$A78))/6,"") -> 0.25263158 | H78: =IF(COUNTIF(RawData!$D:$D,$A78) > 0, (SUMIF(RawData!$D:$D,$A78,RawData!$H:$H)/COUNTIF(RawData!$D:$D,$A78))/6,"") -> 0.33157895 | I78: =IF(COUNTIF(RawData!$D:$D,$A78) > 0, (COUNTIFS(RawData!$D:$D,$A78,RawData!L:L,0)/COUNTIF(RawData!$D:$D,$A78)),"") -> 0.30526316
A79: 3 | B79: Неделя 3 | C79: =IF(COUNTIF(RawData!$D:$D,$A79) > 0, (SUMIF(RawData!$D:$D,$A79,RawData!$L:$L)/COUNTIF(RawData!$D:$D,$A79))/3,"") -> -0.095785441 | D79: =IF(COUNTIF(RawData!$D:$D,$A79) > 0, (SUMIF(RawData!$D:$D,$A79,RawData!$K:$K)/COUNTIF(RawData!$D:$D,$A79))/3,"") -> -0.026819923 | E79: =IF(COUNTIF(RawData!$D:$D,$A79) > 0, (SUMIF(RawData!$D:$D,$A79,RawData!$J:$J)/COUNTIF(RawData!$D:$D,$A79))/6,"") -> 0.75095785 | F79: =IF(COUNTIF(RawData!$D:$D,$A79) > 0, (SUMIF(RawData!$D:$D,$A79,RawData!$G:$G)/COUNTIF(RawData!$D:$D,$A79))/6,"") -> 0.29693487 | G79: =IF(COUNTIF(RawData!$D:$D,$A79) > 0, (SUMIF(RawData!$D:$D,$A79,RawData!$F:$F)/COUNTIF(RawData!$D:$D,$A79))/6,"") -> 0.28544061 | H79: =IF(COUNTIF(RawData!$D:$D,$A79) > 0, (SUMIF(RawData!$D:$D,$A79,RawData!$H:$H)/COUNTIF(RawData!$D:$D,$A79))/6,"") -> 0.35632184 | I79: =IF(COUNTIF(RawData!$D:$D,$A79) > 0, (COUNTIFS(RawData!$D:$D,$A79,RawData!L:L,0)/COUNTIF(RawData!$D:$D,$A79)),"") -> 0.24137931
A80: 4 | B80: Неделя 4 | C80: =IF(COUNTIF(RawData!$D:$D,$A80) > 0, (SUMIF(RawData!$D:$D,$A80,RawData!$L:$L)/COUNTIF(RawData!$D:$D,$A80))/3,"") -> -0.082191781 | D80: =IF(COUNTIF(RawData!$D:$D,$A80) > 0, (SUMIF(RawData!$D:$D,$A80,RawData!$K:$K)/COUNTIF(RawData!$D:$D,$A80))/3,"") -> 0.059360731 | E80: =IF(COUNTIF(RawData!$D:$D,$A80) > 0, (SUMIF(RawData!$D:$D,$A80,RawData!$J:$J)/COUNTIF(RawData!$D:$D,$A80))/6,"") -> 0.79223744 | F80: =IF(COUNTIF(RawData!$D:$D,$A80) > 0, (SUMIF(RawData!$D:$D,$A80,RawData!$G:$G)/COUNTIF(RawData!$D:$D,$A80))/6,"") -> 0.29452055 | G80: =IF(COUNTIF(RawData!$D:$D,$A80) > 0, (SUMIF(RawData!$D:$D,$A80,RawData!$F:$F)/COUNTIF(RawData!$D:$D,$A80))/6,"") -> 0.27625571 | H80: =IF(COUNTIF(RawData!$D:$D,$A80) > 0, (SUMIF(RawData!$D:$D,$A80,RawData!$H:$H)/COUNTIF(RawData!$D:$D,$A80))/6,"") -> 0.37899543 | I80: =IF(COUNTIF(RawData!$D:$D,$A80) > 0, (COUNTIFS(RawData!$D:$D,$A80,RawData!L:L,0)/COUNTIF(RawData!$D:$D,$A80)),"") -> 0.17808219
A81: 5 | B81: Неделя 5 | C81: =IF(COUNTIF(RawData!$D:$D,$A81) > 0, (SUMIF(RawData!$D:$D,$A81,RawData!$L:$L)/COUNTIF(RawData!$D:$D,$A81))/3,"") -> 0.02259887 | D81: =IF(COUNTIF(RawData!$D:$D,$A81) > 0, (SUMIF(RawData!$D:$D,$A81,RawData!$K:$K)/COUNTIF(RawData!$D:$D,$A81))/3,"") -> 0.04519774 | E81: =IF(COUNTIF(RawData!$D:$D,$A81) > 0, (SUMIF(RawData!$D:$D,$A81,RawData!$J:$J)/COUNTIF(RawData!$D:$D,$A81))/6,"") -> 0.83050847 | F81: =IF(COUNTIF(RawData!$D:$D,$A81) > 0, (SUMIF(RawData!$D:$D,$A81,RawData!$G:$G)/COUNTIF(RawData!$D:$D,$A81))/6,"") -> 0.31920904 | G81: =IF(COUNTIF(RawData!$D:$D,$A81) > 0, (SUMIF(RawData!$D:$D,$A81,RawData!$F:$F)/COUNTIF(RawData!$D:$D,$A81))/6,"") -> 0.25423729 | H81: =IF(COUNTIF(RawData!$D:$D,$A81) > 0, (SUMIF(RawData!$D:$D,$A81,RawData!$H:$H)/COUNTIF(RawData!$D:$D,$A81))/6,"") -> 0.38700565 | I81: =IF(COUNTIF(RawData!$D:$D,$A81) > 0, (COUNTIFS(RawData!$D:$D,$A81,RawData!L:L,0)/COUNTIF(RawData!$D:$D,$A81)),"") -> 0.18644068
A82: 6 | B82: Неделя 6 | C82: =IF(COUNTIF(RawData!$D:$D,$A82) > 0, (SUMIF(RawData!$D:$D,$A82,RawData!$L:$L)/COUNTIF(RawData!$D:$D,$A82))/3,"") -> -0.079096045 | D82: =IF(COUNTIF(RawData!$D:$D,$A82) > 0, (SUMIF(RawData!$D:$D,$A82,RawData!$K:$K)/COUNTIF(RawData!$D:$D,$A82))/3,"") -> 0.050847458 | E82: =IF(COUNTIF(RawData!$D:$D,$A82) > 0, (SUMIF(RawData!$D:$D,$A82,RawData!$J:$J)/COUNTIF(RawData!$D:$D,$A82))/6,"") -> 0.77966102 | F82: =IF(COUNTIF(RawData!$D:$D,$A82) > 0, (SUMIF(RawData!$D:$D,$A82,RawData!$G:$G)/COUNTIF(RawData!$D:$D,$A82))/6,"") -> 0.3220339 | G82: =IF(COUNTIF(RawData!$D:$D,$A82) > 0, (SUMIF(RawData!$D:$D,$A82,RawData!$F:$F)/COUNTIF(RawData!$D:$D,$A82))/6,"") -> 0.28813559 | H82: =IF(COUNTIF(RawData!$D:$D,$A82) > 0, (SUMIF(RawData!$D:$D,$A82,RawData!$H:$H)/COUNTIF(RawData!$D:$D,$A82))/6,"") -> 0.33050847 | I82: =IF(COUNTIF(RawData!$D:$D,$A82) > 0, (COUNTIFS(RawData!$D:$D,$A82,RawData!L:L,0)/COUNTIF(RawData!$D:$D,$A82)),"") -> 0.22033898
A83: 7 | B83: Неделя 7 | C83: =IF(COUNTIF(RawData!$D:$D,$A83) > 0, (SUMIF(RawData!$D:$D,$A83,RawData!$L:$L)/COUNTIF(RawData!$D:$D,$A83))/3,"") -> -0.053763441 | D83: =IF(COUNTIF(RawData!$D:$D,$A83) > 0, (SUMIF(RawData!$D:$D,$A83,RawData!$K:$K)/COUNTIF(RawData!$D:$D,$A83))/3,"") -> 0.010752688 | E83: =IF(COUNTIF(RawData!$D:$D,$A83) > 0, (SUMIF(RawData!$D:$D,$A83,RawData!$J:$J)/COUNTIF(RawData!$D:$D,$A83))/6,"") -> 0.76344086 | F83: =IF(COUNTIF(RawData!$D:$D,$A83) > 0, (SUMIF(RawData!$D:$D,$A83,RawData!$G:$G)/COUNTIF(RawData!$D:$D,$A83))/6,"") -> 0.2688172 | G83: =IF(COUNTIF(RawData!$D:$D,$A83) > 0, (SUMIF(RawData!$D:$D,$A83,RawData!$F:$F)/COUNTIF(RawData!$D:$D,$A83))/6,"") -> 0.27688172 | H83: =IF(COUNTIF(RawData!$D:$D,$A83) > 0, (SUMIF(RawData!$D:$D,$A83,RawData!$H:$H)/COUNTIF(RawData!$D:$D,$A83))/6,"") -> 0.36290323 | I83: =IF(COUNTIF(RawData!$D:$D,$A83) > 0, (COUNTIFS(RawData!$D:$D,$A83,RawData!L:L,0)/COUNTIF(RawData!$D:$D,$A83)),"") -> 0.25806452
A84: 8 | B84: Неделя 8 | C84: =IF(COUNTIF(RawData!$D:$D,$A84) > 0, (SUMIF(RawData!$D:$D,$A84,RawData!$L:$L)/COUNTIF(RawData!$D:$D,$A84))/3,"") -> 0.15789474 | D84: =IF(COUNTIF(RawData!$D:$D,$A84) > 0, (SUMIF(RawData!$D:$D,$A84,RawData!$K:$K)/COUNTIF(RawData!$D:$D,$A84))/3,"") -> 0 | E84: =IF(COUNTIF(RawData!$D:$D,$A84) > 0, (SUMIF(RawData!$D:$D,$A84,RawData!$J:$J)/COUNTIF(RawData!$D:$D,$A84))/6,"") -> 0.71052632 | F84: =IF(COUNTIF(RawData!$D:$D,$A84) > 0, (SUMIF(RawData!$D:$D,$A84,RawData!$G:$G)/COUNTIF(RawData!$D:$D,$A84))/6,"") -> 0.29824561 | G84: =IF(COUNTIF(RawData!$D:$D,$A84) > 0, (SUMIF(RawData!$D:$D,$A84,RawData!$F:$F)/COUNTIF(RawData!$D:$D,$A84))/6,"") -> 0.28947368 | H84: =IF(COUNTIF(RawData!$D:$D,$A84) > 0, (SUMIF(RawData!$D:$D,$A84,RawData!$H:$H)/COUNTIF(RawData!$D:$D,$A84))/6,"") -> 0.35087719 | I84: =IF(COUNTIF(RawData!$D:$D,$A84) > 0, (COUNTIFS(RawData!$D:$D,$A84,RawData!L:L,0)/COUNTIF(RawData!$D:$D,$A84)),"") -> 0.26315789
A85: 9 | B85: Неделя 9 | C85: =IF(COUNTIF(RawData!$D:$D,$A85) > 0, (SUMIF(RawData!$D:$D,$A85,RawData!$L:$L)/COUNTIF(RawData!$D:$D,$A85))/3,"") | D85: =IF(COUNTIF(RawData!$D:$D,$A85) > 0, (SUMIF(RawData!$D:$D,$A85,RawData!$K:$K)/COUNTIF(RawData!$D:$D,$A85))/3,"") | E85: =IF(COUNTIF(RawData!$D:$D,$A85) > 0, (SUMIF(RawData!$D:$D,$A85,RawData!$J:$J)/COUNTIF(RawData!$D:$D,$A85))/6,"") | F85: =IF(COUNTIF(RawData!$D:$D,$A85) > 0, (SUMIF(RawData!$D:$D,$A85,RawData!$G:$G)/COUNTIF(RawData!$D:$D,$A85))/6,"") | G85: =IF(COUNTIF(RawData!$D:$D,$A85) > 0, (SUMIF(RawData!$D:$D,$A85,RawData!$F:$F)/COUNTIF(RawData!$D:$D,$A85))/6,"") | H85: =IF(COUNTIF(RawData!$D:$D,$A85) > 0, (SUMIF(RawData!$D:$D,$A85,RawData!$H:$H)/COUNTIF(RawData!$D:$D,$A85))/6,"") | I85: =IF(COUNTIF(RawData!$D:$D,$A85) > 0, (COUNTIFS(RawData!$D:$D,$A85,RawData!L:L,0)/COUNTIF(RawData!$D:$D,$A85)),"")
A86: 10 | B86: Неделя 10 | C86: =IF(COUNTIF(RawData!$D:$D,$A86) > 0, (SUMIF(RawData!$D:$D,$A86,RawData!$L:$L)/COUNTIF(RawData!$D:$D,$A86))/3,"") | D86: =IF(COUNTIF(RawData!$D:$D,$A86) > 0, (SUMIF(RawData!$D:$D,$A86,RawData!$K:$K)/COUNTIF(RawData!$D:$D,$A86))/3,"") | E86: =IF(COUNTIF(RawData!$D:$D,$A86) > 0, (SUMIF(RawData!$D:$D,$A86,RawData!$J:$J)/COUNTIF(RawData!$D:$D,$A86))/6,"") | F86: =IF(COUNTIF(RawData!$D:$D,$A86) > 0, (SUMIF(RawData!$D:$D,$A86,RawData!$G:$G)/COUNTIF(RawData!$D:$D,$A86))/6,"") | G86: =IF(COUNTIF(RawData!$D:$D,$A86) > 0, (SUMIF(RawData!$D:$D,$A86,RawData!$F:$F)/COUNTIF(RawData!$D:$D,$A86))/6,"") | H86: =IF(COUNTIF(RawData!$D:$D,$A86) > 0, (SUMIF(RawData!$D:$D,$A86,RawData!$H:$H)/COUNTIF(RawData!$D:$D,$A86))/6,"") | I86: =IF(COUNTIF(RawData!$D:$D,$A86) > 0, (COUNTIFS(RawData!$D:$D,$A86,RawData!L:L,0)/COUNTIF(RawData!$D:$D,$A86)),"")
A87: 11 | B87: Неделя 11 | C87: =IF(COUNTIF(RawData!$D:$D,$A87) > 0, (SUMIF(RawData!$D:$D,$A87,RawData!$L:$L)/COUNTIF(RawData!$D:$D,$A87))/3,"") | D87: =IF(COUNTIF(RawData!$D:$D,$A87) > 0, (SUMIF(RawData!$D:$D,$A87,RawData!$K:$K)/COUNTIF(RawData!$D:$D,$A87))/3,"") | E87: =IF(COUNTIF(RawData!$D:$D,$A87) > 0, (SUMIF(RawData!$D:$D,$A87,RawData!$J:$J)/COUNTIF(RawData!$D:$D,$A87))/6,"") | F87: =IF(COUNTIF(RawData!$D:$D,$A87) > 0, (SUMIF(RawData!$D:$D,$A87,RawData!$G:$G)/COUNTIF(RawData!$D:$D,$A87))/6,"") | G87: =IF(COUNTIF(RawData!$D:$D,$A87) > 0, (SUMIF(RawData!$D:$D,$A87,RawData!$F:$F)/COUNTIF(RawData!$D:$D,$A87))/6,"") | H87: =IF(COUNTIF(RawData!$D:$D,$A87) > 0, (SUMIF(RawData!$D:$D,$A87,RawData!$H:$H)/COUNTIF(RawData!$D:$D,$A87))/6,"") | I87: =IF(COUNTIF(RawData!$D:$D,$A87) > 0, (COUNTIFS(RawData!$D:$D,$A87,RawData!L:L,0)/COUNTIF(RawData!$D:$D,$A87)),"")
A88: 12 | B88: Неделя 12 | C88: =IF(COUNTIF(RawData!$D:$D,$A88) > 0, (SUMIF(RawData!$D:$D,$A88,RawData!$L:$L)/COUNTIF(RawData!$D:$D,$A88))/3,"") | D88: =IF(COUNTIF(RawData!$D:$D,$A88) > 0, (SUMIF(RawData!$D:$D,$A88,RawData!$K:$K)/COUNTIF(RawData!$D:$D,$A88))/3,"") | E88: =IF(COUNTIF(RawData!$D:$D,$A88) > 0, (SUMIF(RawData!$D:$D,$A88,RawData!$J:$J)/COUNTIF(RawData!$D:$D,$A88))/6,"") | F88: =IF(COUNTIF(RawData!$D:$D,$A88) > 0, (SUMIF(RawData!$D:$D,$A88,RawData!$G:$G)/COUNTIF(RawData!$D:$D,$A88))/6,"") | G88: =IF(COUNTIF(RawData!$D:$D,$A88) > 0, (SUMIF(RawData!$D:$D,$A88,RawData!$F:$F)/COUNTIF(RawData!$D:$D,$A88))/6,"") | H88: =IF(COUNTIF(RawData!$D:$D,$A88) > 0, (SUMIF(RawData!$D:$D,$A88,RawData!$H:$H)/COUNTIF(RawData!$D:$D,$A88))/6,"") | I88: =IF(COUNTIF(RawData!$D:$D,$A88) > 0, (COUNTIFS(RawData!$D:$D,$A88,RawData!L:L,0)/COUNTIF(RawData!$D:$D,$A88)),"")
C97: Средний фактор дистресса | D97: Средний фактор совладания | E97: Низкий стресс | F97: Средний стресс | G97: Высокий стресс
A98: 0 | B98: Неделя 0 | C98: =IF(COUNTIF(RawData!$D:$D,$A98) > 0, (SUMIF(RawData!$D:$D,$A98,RawData!$U:$U)/COUNTIF(RawData!$D:$D,$A98))/8,"") -> 0.47146739 | D98: =IF(COUNTIF(RawData!$D:$D,$A98) > 0, (SUMIF(RawData!$D:$D,$A98,RawData!$V:$V)/COUNTIF(RawData!$D:$D,$A98))/8,"") -> 0.61820652 | E98: =IF(COUNTIF(RawData!$D:$D,$A98) > 0, (COUNTIFS(RawData!$D:$D,$A98,RawData!$W:$W,"<=4")/COUNTIF(RawData!$D:$D,$A98)),"") -> 0.27173913 | F98: =IF(COUNTIF(RawData!$D:$D,$A98) > 0, (COUNTIFS(RawData!$D:$D,$A98,RawData!$W:$W,"<9",RawData!$W:$W,">4")/COUNTIF(RawData!$D:$D,$A98)),"") -> 0.44565217 | G98: =IF(COUNTIF(RawData!$D:$D,$A98) > 0, (COUNTIFS(RawData!$D:$D,$A98,RawData!$W:$W,">=9")/COUNTIF(RawData!$D:$D,$A98)),"") -> 0.2826087
A99: 1 | B99: Неделя 1 | C99: =IF(COUNTIF(RawData!$D:$D,$A99) > 0, (SUMIF(RawData!$D:$D,$A99,RawData!$U:$U)/COUNTIF(RawData!$D:$D,$A99))/8,"") -> 0.46447368 | D99: =IF(COUNTIF(RawData!$D:$D,$A99) > 0, (SUMIF(RawData!$D:$D,$A99,RawData!$V:$V)/COUNTIF(RawData!$D:$D,$A99))/8,"") -> 0.61973684 | E99: =IF(COUNTIF(RawData!$D:$D,$A99) > 0, (COUNTIFS(RawData!$D:$D,$A99,RawData!$W:$W,"<=4")/COUNTIF(RawData!$D:$D,$A99)),"") -> 0.23157895 | F99: =IF(COUNTIF(RawData!$D:$D,$A99) > 0, (COUNTIFS(RawData!$D:$D,$A99,RawData!$W:$W,"<9",RawData!$W:$W,">4")/COUNTIF(RawData!$D:$D,$A99)),"") -> 0.53684211 | G99: =IF(COUNTIF(RawData!$D:$D,$A99) > 0, (COUNTIFS(RawData!$D:$D,$A99,RawData!$W:$W,">=9")/COUNTIF(RawData!$D:$D,$A99)),"") -> 0.23157895
A100: 2 | B100: Неделя 2 | C100: =IF(COUNTIF(RawData!$D:$D,$A100) > 0, (SUMIF(RawData!$D:$D,$A100,RawData!$U:$U)/COUNTIF(RawData!$D:$D,$A100))/8,"") -> 0.40263158 | D100: =IF(COUNTIF(RawData!$D:$D,$A100) > 0, (SUMIF(RawData!$D:$D,$A100,RawData!$V:$V)/COUNTIF(RawData!$D:$D,$A100))/8,"") -> 0.63947368 | E100: =IF(COUNTIF(RawData!$D:$D,$A100) > 0, (COUNTIFS(RawData!$D:$D,$A100,RawData!$W:$W,"<=4")/COUNTIF(RawData!$D:$D,$A100)),"") -> 0.27368421 | F100: =IF(COUNTIF(RawData!$D:$D,$A100) > 0, (COUNTIFS(RawData!$D:$D,$A100,RawData!$W:$W,"<9",RawData!$W:$W,">4")/COUNTIF(RawData!$D:$D,$A100)),"") -> 0.56842105 | G100: =IF(COUNTIF(RawData!$D:$D,$A100) > 0, (COUNTIFS(RawData!$D:$D,$A100,RawData!$W:$W,">=9")/COUNTIF(RawData!$D:$D,$A100)),"") -> 0.15789474
A101: 3 | B101: Неделя 3 | C101: =IF(COUNTIF(RawData!$D:$D,$A101) > 0, (SUMIF(RawData!$D:$D,$A101,RawData!$U:$U)/COUNTIF(RawData!$D:$D,$A101))/8,"") -> 0.40804598 | D101: =IF(COUNTIF(RawData!$D:$D,$A101) > 0, (SUMIF(RawData!$D:$D,$A101,RawData!$V:$V)/COUNTIF(RawData!$D:$D,$A101))/8,"") -> 0.63936782 | E101: =IF(COUNTIF(RawData!$D:$D,$A101) > 0, (COUNTIFS(RawData!$D:$D,$A101,RawData!$W:$W,"<=4")/COUNTIF(RawData!$D:$D,$A101)),"") -> 0.31034483 | F101: =IF(COUNTIF(RawData!$D:$D,$A101) > 0, (COUNTIFS(RawData!$D:$D,$A101,RawData!$W:$W,"<9",RawData!$W:$W,">4")/COUNTIF(RawData!$D:$D,$A101)),"") -> 0.52873563 | G101: =IF(COUNTIF(RawData!$D:$D,$A101) > 0, (COUNTIFS(RawData!$D:$D,$A101,RawData!$W:$W,">=9")/COUNTIF(RawData!$D:$D,$A101)),"") -> 0.16091954
A102: 4 | B102: Неделя 4 | C102: =IF(COUNTIF(RawData!$D:$D,$A102) > 0, (SUMIF(RawData!$D:$D,$A102,RawData!$U:$U)/COUNTIF(RawData!$D:$D,$A102))/8,"") -> 0.38869863 | D102: =IF(COUNTIF(RawData!$D:$D,$A102) > 0, (SUMIF(RawData!$D:$D,$A102,RawData!$V:$V)/COUNTIF(RawData!$D:$D,$A102))/8,"") -> 0.65410959 | E102: =IF(COUNTIF(RawData!$D:$D,$A102) > 0, (COUNTIFS(RawData!$D:$D,$A102,RawData!$W:$W,"<=4")/COUNTIF(RawData!$D:$D,$A102)),"") -> 0.2739726 | F102: =IF(COUNTIF(RawData!$D:$D,$A102) > 0, (COUNTIFS(RawData!$D:$D,$A102,RawData!$W:$W,"<9",RawData!$W:$W,">4")/COUNTIF(RawData!$D:$D,$A102)),"") -> 0.5890411 | G102: =IF(COUNTIF(RawData!$D:$D,$A102) > 0, (COUNTIFS(RawData!$D:$D,$A102,RawData!$W:$W,">=9")/COUNTIF(RawData!$D:$D,$A102)),"") -> 0.1369863
A103: 5 | B103: Неделя 5 | C103: =IF(COUNTIF(RawData!$D:$D,$A103) > 0, (SUMIF(RawData!$D:$D,$A103,RawData!$U:$U)/COUNTIF(RawData!$D:$D,$A103))/8,"") -> 0.3940678 | D103: =IF(COUNTIF(RawData!$D:$D,$A103) > 0, (SUMIF(RawData!$D:$D,$A103,RawData!$V:$V)/COUNTIF(RawData!$D:$D,$A103))/8,"") -> 0.62288136 | E103: =IF(COUNTIF(RawData!$D:$D,$A103) > 0, (COUNTIFS(RawData!$D:$D,$A103,RawData!$W:$W,"<=4")/COUNTIF(RawData!$D:$D,$A103)),"") -> 0.23728814 | F103: =IF(COUNTIF(RawData!$D:$D,$A103) > 0, (COUNTIFS(RawData!$D:$D,$A103,RawData!$W:$W,"<9",RawData!$W:$W,">4")/COUNTIF(RawData!$D:$D,$A103)),"") -> 0.62711864 | G103: =IF(COUNTIF(RawData!$D:$D,$A103) > 0, (COUNTIFS(RawData!$D:$D,$A103,RawData!$W:$W,">=9")/COUNTIF(RawData!$D:$D,$A103)),"") -> 0.13559322
A104: 6 | B104: Неделя 6 | C104: =IF(COUNTIF(RawData!$D:$D,$A104) > 0, (SUMIF(RawData!$D:$D,$A104,RawData!$U:$U)/COUNTIF(RawData!$D:$D,$A104))/8,"") -> 0.39618644 | D104: =IF(COUNTIF(RawData!$D:$D,$A104) > 0, (SUMIF(RawData!$D:$D,$A104,RawData!$V:$V)/COUNTIF(RawData!$D:$D,$A104))/8,"") -> 0.61864407 | E104: =IF(COUNTIF(RawData!$D:$D,$A104) > 0, (COUNTIFS(RawData!$D:$D,$A104,RawData!$W:$W,"<=4")/COUNTIF(RawData!$D:$D,$A104)),"") -> 0.23728814 | F104: =IF(COUNTIF(RawData!$D:$D,$A104) > 0, (COUNTIFS(RawData!$D:$D,$A104,RawData!$W:$W,"<9",RawData!$W:$W,">4")/COUNTIF(RawData!$D:$D,$A104)),"") -> 0.62711864 | G104: =IF(COUNTIF(RawData!$D:$D,$A104) > 0, (COUNTIFS(RawData!$D:$D,$A104,RawData!$W:$W,">=9")/COUNTIF(RawData!$D:$D,$A104)),"") -> 0.13559322
A105: 7 | B105: Неделя 7 | C105: =IF(COUNTIF(RawData!$D:$D,$A105) > 0, (SUMIF(RawData!$D:$D,$A105,RawData!$U:$U)/COUNTIF(RawData!$D:$D,$A105))/8,"") -> 0.40322581 | D105: =IF(COUNTIF(RawData!$D:$D,$A105) > 0, (SUMIF(RawData!$D:$D,$A105,RawData!$V:$V)/COUNTIF(RawData!$D:$D,$A105))/8,"") -> 0.62298387 | E105: =IF(COUNTIF(RawData!$D:$D,$A105) > 0, (COUNTIFS(RawData!$D:$D,$A105,RawData!$W:$W,"<=4")/COUNTIF(RawData!$D:$D,$A105)),"") -> 0.32258065 | F105: =IF(COUNTIF(RawData!$D:$D,$A105) > 0, (COUNTIFS(RawData!$D:$D,$A105,RawData!$W:$W,"<9",RawData!$W:$W,">4")/COUNTIF(RawData!$D:$D,$A105)),"") -> 0.48387097 | G105: =IF(COUNTIF(RawData!$D:$D,$A105) > 0, (COUNTIFS(RawData!$D:$D,$A105,RawData!$W:$W,">=9")/COUNTIF(RawData!$D:$D,$A105)),"") -> 0.19354839
A106: 8 | B106: Неделя 8 | C106: =IF(COUNTIF(RawData!$D:$D,$A106) > 0, (SUMIF(RawData!$D:$D,$A106,RawData!$U:$U)/COUNTIF(RawData!$D:$D,$A106))/8,"") -> 0.44078947 | D106: =IF(COUNTIF(RawData!$D:$D,$A106) > 0, (SUMIF(RawData!$D:$D,$A106,RawData!$V:$V)/COUNTIF(RawData!$D:$D,$A106))/8,"") -> 0.54605263 | E106: =IF(COUNTIF(RawData!$D:$D,$A106) > 0, (COUNTIFS(RawData!$D:$D,$A106,RawData!$W:$W,"<=4")/COUNTIF(RawData!$D:$D,$A106)),"") -> 0.21052632 | F106: =IF(COUNTIF(RawData!$D:$D,$A106) > 0, (COUNTIFS(RawData!$D:$D,$A106,RawData!$W:$W,"<9",RawData!$W:$W,">4")/COUNTIF(RawData!$D:$D,$A106)),"") -> 0.42105263 | G106: =IF(COUNTIF(RawData!$D:$D,$A106) > 0, (COUNTIFS(RawData!$D:$D,$A106,RawData!$W:$W,">=9")/COUNTIF(RawData!$D:$D,$A106)),"") -> 0.36842105
A107: 9 | B107: Неделя 9 | C107: =IF(COUNTIF(RawData!$D:$D,$A107) > 0, (SUMIF(RawData!$D:$D,$A107,RawData!$U:$U)/COUNTIF(RawData!$D:$D,$A107))/8,"") | D107: =IF(COUNTIF(RawData!$D:$D,$A107) > 0, (SUMIF(RawData!$D:$D,$A107,RawData!$V:$V)/COUNTIF(RawData!$D:$D,$A107))/8,"") | E107: =IF(COUNTIF(RawData!$D:$D,$A107) > 0, (COUNTIFS(RawData!$D:$D,$A107,RawData!$W:$W,"<=4")/COUNTIF(RawData!$D:$D,$A107)),"") | F107: =IF(COUNTIF(RawData!$D:$D,$A107) > 0, (COUNTIFS(RawData!$D:$D,$A107,RawData!$W:$W,"<9",RawData!$W:$W,">4")/COUNTIF(RawData!$D:$D,$A107)),"") | G107: =IF(COUNTIF(RawData!$D:$D,$A107) > 0, (COUNTIFS(RawData!$D:$D,$A107,RawData!$W:$W,">=9")/COUNTIF(RawData!$D:$D,$A107)),"")
A108: 10 | B108: Неделя 10 | C108: =IF(COUNTIF(RawData!$D:$D,$A108) > 0, (SUMIF(RawData!$D:$D,$A108,RawData!$U:$U)/COUNTIF(RawData!$D:$D,$A108))/8,"") | D108: =IF(COUNTIF(RawData!$D:$D,$A108) > 0, (SUMIF(RawData!$D:$D,$A108,RawData!$V:$V)/COUNTIF(RawData!$D:$D,$A108))/8,"") | E108: =IF(COUNTIF(RawData!$D:$D,$A108) > 0, (COUNTIFS(RawData!$D:$D,$A108,RawData!$W:$W,"<=4")/COUNTIF(RawData!$D:$D,$A108)),"") | F108: =IF(COUNTIF(RawData!$D:$D,$A108) > 0, (COUNTIFS(RawData!$D:$D,$A108,RawData!$W:$W,"<9",RawData!$W:$W,">4")/COUNTIF(RawData!$D:$D,$A108)),"") | G108: =IF(COUNTIF(RawData!$D:$D,$A108) > 0, (COUNTIFS(RawData!$D:$D,$A108,RawData!$W:$W,">=9")/COUNTIF(RawData!$D:$D,$A108)),"")
A109: 11 | B109: Неделя 11 | C109: =IF(COUNTIF(RawData!$D:$D,$A109) > 0, (SUMIF(RawData!$D:$D,$A109,RawData!$U:$U)/COUNTIF(RawData!$D:$D,$A109))/8,"") | D109: =IF(COUNTIF(RawData!$D:$D,$A109) > 0, (SUMIF(RawData!$D:$D,$A109,RawData!$V:$V)/COUNTIF(RawData!$D:$D,$A109))/8,"") | E109: =IF(COUNTIF(RawData!$D:$D,$A109) > 0, (COUNTIFS(RawData!$D:$D,$A109,RawData!$W:$W,"<=4")/COUNTIF(RawData!$D:$D,$A109)),"") | F109: =IF(COUNTIF(RawData!$D:$D,$A109) > 0, (COUNTIFS(RawData!$D:$D,$A109,RawData!$W:$W,"<9",RawData!$W:$W,">4")/COUNTIF(RawData!$D:$D,$A109)),"") | G109: =IF(COUNTIF(RawData!$D:$D,$A109) > 0, (COUNTIFS(RawData!$D:$D,$A109,RawData!$W:$W,">=9")/COUNTIF(RawData!$D:$D,$A109)),"")
A110: 12 | B110: Неделя 12 | C110: =IF(COUNTIF(RawData!$D:$D,$A110) > 0, (SUMIF(RawData!$D:$D,$A110,RawData!$U:$U)/COUNTIF(RawData!$D:$D,$A110))/8,"") | D110: =IF(COUNTIF(RawData!$D:$D,$A110) > 0, (SUMIF(RawData!$D:$D,$A110,RawData!$V:$V)/COUNTIF(RawData!$D:$D,$A110))/8,"") | E110: =IF(COUNTIF(RawData!$D:$D,$A110) > 0, (COUNTIFS(RawData!$D:$D,$A110,RawData!$W:$W,"<=4")/COUNTIF(RawData!$D:$D,$A110)),"") | F110: =IF(COUNTIF(RawData!$D:$D,$A110) > 0, (COUNTIFS(RawData!$D:$D,$A110,RawData!$W:$W,"<9",RawData!$W:$W,">4")/COUNTIF(RawData!$D:$D,$A110)),"") | G110: =IF(COUNTIF(RawData!$D:$D,$A110) > 0, (COUNTIFS(RawData!$D:$D,$A110,RawData!$W:$W,">=9")/COUNTIF(RawData!$D:$D,$A110)),"")

Sheet По человекам
A2: Участник | B2: asya_in_motion
C3: Средний фактор дистресса | D3: Средний фактор совладания
A4: 0 | B4: Неделя 0 | C4: =IF(COUNTIFS(RawData!$D:$D,$A4,RawData!C:C, $B$2) > 0, (SUMIFS(RawData!$U:$U,RawData!$D:$D,$A4,RawData!C:C, $B$2))/(8*COUNTIFS(RawData!$D:$D,$A4,RawData!C:C, $B$2)),"") -> 0.625 | D4: =IF(COUNTIFS(RawData!$D:$D,$A4,RawData!C:C, $B$2) > 0, (SUMIFS(RawData!$V:$V,RawData!$D:$D,$A4,RawData!C:C, $B$2)/COUNTIFS(RawData!$D:$D,$A4,RawData!C:C, $B$2))/8,"") -> 0.5
A5: 1 | B5: Неделя 1 | C5: =IF(COUNTIFS(RawData!$D:$D,$A5,RawData!C:C, $B$2) > 0, (SUMIFS(RawData!$U:$U,RawData!$D:$D,$A5,RawData!C:C, $B$2))/(8*COUNTIFS(RawData!$D:$D,$A5,RawData!C:C, $B$2)),"") | D5: =IF(COUNTIFS(RawData!$D:$D,$A5,RawData!C:C, $B$2) > 0, (SUMIFS(RawData!$V:$V,RawData!$D:$D,$A5,RawData!C:C, $B$2)/COUNTIFS(RawData!$D:$D,$A5,RawData!C:C, $B$2))/8,"")
A6: 2 | B6: Неделя 2 | C6: =IF(COUNTIFS(RawData!$D:$D,$A6,RawData!C:C, $B$2) > 0, (SUMIFS(RawData!$U:$U,RawData!$D:$D,$A6,RawData!C:C, $B$2))/(8*COUNTIFS(RawData!$D:$D,$A6,RawData!C:C, $B$2)),"") -> 0.5 | D6: =IF(COUNTIFS(RawData!$D:$D,$A6,RawData!C:C, $B$2) > 0, (SUMIFS(RawData!$V:$V,RawData!$D:$D,$A6,RawData!C:C, $B$2)/COUNTIFS(RawData!$D:$D,$A6,RawData!C:C, $B$2))/8,"") -> 0.375
A7: 3 | B7: Неделя 3 | C7: =IF(COUNTIFS(RawData!$D:$D,$A7,RawData!C:C, $B$2) > 0, (SUMIFS(RawData!$U:$U,RawData!$D:$D,$A7,RawData!C:C, $B$2))/(8*COUNTIFS(RawData!$D:$D,$A7,RawData!C:C, $B$2)),"") -> 0.875 | D7: =IF(COUNTIFS(RawData!$D:$D,$A7,RawData!C:C, $B$2) > 0, (SUMIFS(RawData!$V:$V,RawData!$D:$D,$A7,RawData!C:C, $B$2)/COUNTIFS(RawData!$D:$D,$A7,RawData!C:C, $B$2))/8,"") -> 0.75
A8: 4 | B8: Неделя 4 | C8: =IF(COUNTIFS(RawData!$D:$D,$A8,RawData!C:C, $B$2) > 0, (SUMIFS(RawData!$U:$U,RawData!$D:$D,$A8,RawData!C:C, $B$2))/(8*COUNTIFS(RawData!$D:$D,$A8,RawData!C:C, $B$2)),"") -> 1 | D8: =IF(COUNTIFS(RawData!$D:$D,$A8,RawData!C:C, $B$2) > 0, (SUMIFS(RawData!$V:$V,RawData!$D:$D,$A8,RawData!C:C, $B$2)/COUNTIFS(RawData!$D:$D,$A8,RawData!C:C, $B$2))/8,"") -> 0.625
A9: 5 | B9: Неделя 5 | C9: =IF(COUNTIFS(RawData!$D:$D,$A9,RawData!C:C, $B$2) > 0, (SUMIFS(RawData!$U:$U,RawData!$D:$D,$A9,RawData!C:C, $B$2))/(8*COUNTIFS(RawData!$D:$D,$A9,RawData!C:C, $B$2)),"") | D9: =IF(COUNTIFS(RawData!$D:$D,$A9,RawData!C:C, $B$2) > 0, (SUMIFS(RawData!$V:$V,RawData!$D:$D,$A9,RawData!C:C, $B$2)/COUNTIFS(RawData!$D:$D,$A9,RawData!C:C, $B$2))/8,"")
A10: 6 | B10: Неделя 6 | C10: =IF(COUNTIFS(RawData!$D:$D,$A10,RawData!C:C, $B$2) > 0, (SUMIFS(RawData!$U:$U,RawData!$D:$D,$A10,RawData!C:C, $B$2))/(8*COUNTIFS(RawData!$D:$D,$A10,RawData!C:C, $B$2)),"") -> 0.625 | D10: =IF(COUNTIFS(RawData!$D:$D,$A10,RawData!C:C, $B$2) > 0, (SUMIFS(RawData!$V:$V,RawData!$D:$D,$A10,RawData!C:C, $B$2)/COUNTIFS(RawData!$D:$D,$A10,RawData!C:C, $B$2))/8,"") -> 0.4375
A11: 7 | B11: Неделя 7 | C11: =IF(COUNTIFS(RawData!$D:$D,$A11,RawData!C:C, $B$2) > 0, (SUMIFS(RawData!$U:$U,RawData!$D:$D,$A11,RawData!C:C, $B$2))/(8*COUNTIFS(RawData!$D:$D,$A11,RawData!C:C, $B$2)),"") | D11: =IF(COUNTIFS(RawData!$D:$D,$A11,RawData!C:C, $B$2) > 0, (SUMIFS(RawData!$V:$V,RawData!$D:$D,$A11,RawData!C:C, $B$2)/COUNTIFS(RawData!$D:$D,$A11,RawData!C:C, $B$2))/8,"")
A12: 8 | B12: Неделя 8 | C12: =IF(COUNTIFS(RawData!$D:$D,$A12,RawData!C:C, $B$2) > 0, (SUMIFS(RawData!$U:$U,RawData!$D:$D,$A12,RawData!C:C, $B$2))/(8*COUNTIFS(RawData!$D:$D,$A12,RawData!C:C, $B$2)),"") -> 0.5 | D12: =IF(COUNTIFS(RawData!$D:$D,$A12,RawData!C:C, $B$2) > 0, (SUMIFS(RawData!$V:$V,RawData!$D:$D,$A12,RawData!C:C, $B$2)/COUNTIFS(RawData!$D:$D,$A12,RawData!C:C, $B$2))/8,"") -> 0.5
A13: 9 | B13: Неделя 9 | C13: =IF(COUNTIFS(RawData!$D:$D,$A13,RawData!C:C, $B$2) > 0, (SUMIFS(RawData!$U:$U,RawData!$D:$D,$A13,RawData!C:C, $B$2))/(8*COUNTIFS(RawData!$D:$D,$A13,RawData!C:C, $B$2)),"") | D13: =IF(COUNTIFS(RawData!$D:$D,$A13,RawData!C:C, $B$2) > 0, (SUMIFS(RawData!$V:$V,RawData!$D:$D,$A13,RawData!C:C, $B$2)/COUNTIFS(RawData!$D:$D,$A13,RawData!C:C, $B$2))/8,"")
A14: 10 | B14: Неделя 10 | C14: =IF(COUNTIFS(RawData!$D:$D,$A14,RawData!C:C, $B$2) > 0, (SUMIFS(RawData!$U:$U,RawData!$D:$D,$A14,RawData!C:C, $B$2))/(8*COUNTIFS(RawData!$D:$D,$A14,RawData!C:C, $B$2)),"") | D14: =IF(COUNTIFS(RawData!$D:$D,$A14,RawData!C:C, $B$2) > 0, (SUMIFS(RawData!$V:$V,RawData!$D:$D,$A14,RawData!C:C, $B$2)/COUNTIFS(RawData!$D:$D,$A14,RawData!C:C, $B$2))/8,"")
A15: 11 | B15: Неделя 11 | C15: =IF(COUNTIFS(RawData!$D:$D,$A15,RawData!C:C, $B$2) > 0, (SUMIFS(RawData!$U:$U,RawData!$D:$D,$A15,RawData!C:C, $B$2))/(8*COUNTIFS(RawData!$D:$D,$A15,RawData!C:C, $B$2)),"") | D15: =IF(COUNTIFS(RawData!$D:$D,$A15,RawData!C:C, $B$2) > 0, (SUMIFS(RawData!$V:$V,RawData!$D:$D,$A15,RawData!C:C, $B$2)/COUNTIFS(RawData!$D:$D,$A15,RawData!C:C, $B$2))/8,"")
A16: 12 | B16: Неделя 12 | C16: =IF(COUNTIFS(RawData!$D:$D,$A16,RawData!C:C, $B$2) > 0, (SUMIFS(RawData!$U:$U,RawData!$D:$D,$A16,RawData!C:C, $B$2))/(8*COUNTIFS(RawData!$D:$D,$A16,RawData!C:C, $B$2)),"") | D16: =IF(COUNTIFS(RawData!$D:$D,$A16,RawData!C:C, $B$2) > 0, (SUMIFS(RawData!$V:$V,RawData!$D:$D,$A16,RawData!C:C, $B$2)/COUNTIFS(RawData!$D:$D,$A16,RawData!C:C, $B$2))/8,"")

Sheet Инсайты
A1: Инсайты
A2: =IFERROR(__xludf.DUMMYFUNCTION("ARRAYFORMULA(FILTER(RawData!Q2:Q1000,RawData!Q2:Q1000<>"""",RawData!D2:D1000=CurSprint) & char(10))"),"Улитка - сила. Пока необузданная сила ") -> Улитка - сила. Пока необузданная сила
A3: =IFERROR(__xludf.DUMMYFUNCTION("""COMPUTED_VALUE"""),"Все преодолимо, когда у тебя есть цель ") -> Все преодолимо, когда у тебя есть цель
A4: =IFERROR(__xludf.DUMMYFUNCTION("""COMPUTED_VALUE"""),"Вести личные и рабочие задачи в одном списке но не могу это делать на выходных ") -> Вести личные и рабочие задачи в одном списке но не могу это делать на выходных

Sheet Комментарии
A1: Комментарии
A2: =IFERROR(__xludf.DUMMYFUNCTION("ARRAYFORMULA(FILTER(RawData!R2:R1000,RawData!R2:R1000<>"""",RawData!D2:D1000=CurSprint) & char(10))"),"Вы красаффчики ") -> Вы красаффчики
